Workbook

Sheet Executive_Summary
B1: Tata SUV Consumer Behaviour - Executive Summary
B2: Hyderabad survey of 135 respondents. Every number on this sheet is a live formula.
B4: Respondents | C4: Prefer an EV | D4: Prefer automatic | E4: Finance with a loan | F4: Most popular model | G4: Largest complaint
B5: =COUNTA(Data!$A$2:$A$136) -> 135 | C5: =COUNTIF(Data!$I$2:$I$136,"EV")/COUNTA(Data!$A$2:$A$136) -> 0.31111111 | D5: =COUNTIF(Data!$J$2:$J$136,"Automatic")/COUNTA(Data!$A$2:$A$136) -> 0.57037037 | E5: =COUNTIF(Data!$S$2:$S$136,"Loan")/COUNTA(Data!$A$2:$A$136) -> 0.74074074 | F5: =INDEX(Demand_Profile!A6:A11,MATCH(MAX(Demand_Profile!B6:B11),Demand_Profile!B6:B11,0)) -> Nexon | G5: =Service_Experience!A22 -> Panel gaps
B7: Key findings
B8: ="1. Demand is concentrated: "&INDEX(Demand_Profile!A6:A11,MATCH(LARGE(Demand_Profile!B6:B11,1),Demand_Profile!B6:B11,0))&" and "&INDEX(Demand_Profile!A6:A11,MATCH(LARGE(Demand_Profile!B6:B11,2),Demand_Profile!B6:B11,0))&" together attract "&TEXT(LARGE(Demand_Profile!C6:C11,1)+LARGE(Demand_Profile!C6:C11,2),"0.0%")&" of all model interest." -> 1. Demand is concentrated: Nexon and Punch together attract 45.9% of all model interest.
B9: ="2. EV interest is highest in the "&INDEX(Powertrain_Transmission!A6:A10,MATCH(MAX(Powertrain_Transmission!D6:D10),Powertrain_Transmission!D6:D10,0))&" age group ("&TEXT(MAX(Powertrain_Transmission!D6:D10),"0.0%")&") and lowest in "&INDEX(Powertrain_Transmission!A6:A10,MATCH(MIN(Powertrain_Transmission!D6:D10),Powertrain_Transmission!D6:D10,0))&" ("&TEXT(MIN(Powertrain_Transmission!D6:D10),"0.0%")&")." -> 2. EV interest is highest in the 26-35 age group (50.0%) and lowest in 36-45 (14.8%).
B10: ="3. EV demand is model-specific: "&TEXT(INDEX(Powertrain_Transmission!G38:G43,MATCH("Nexon",Powertrain_Transmission!A38:A43,0)),"0.0%")&" of Nexon-interested respondents want the EV, versus "&TEXT(INDEX(Powertrain_Transmission!G38:G43,MATCH("Punch",Powertrain_Transmission!A38:A43,0)),"0.0%")&" for Punch." -> 3. EV demand is model-specific: 62.9% of Nexon-interested respondents want the EV, versus 11.1% for Punch.
B11: ="4. Premium-tier interest rises with income: "&TEXT(Demand_Profile!D41,"0.0%")&" in the Above 2L band versus "&TEXT(Demand_Profile!D39,"0.0%")&" in the 50K-1L band." -> 4. Premium-tier interest rises with income: 67.7% in the Above 2L band versus 23.1% in the 50K-1L band.
B12: ="5. Loans are the main payment mode ("&TEXT(E5,"0.0%")&" overall) and peak at "&TEXT(MAX(Buying_Behaviour!F22:F26),"0.0%")&" in the "&INDEX(Buying_Behaviour!A22:A26,MATCH(MAX(Buying_Behaviour!F22:F26),Buying_Behaviour!F22:F26,0))&" group." -> 5. Loans are the main payment mode (74.1% overall) and peak at 85.7% in the 26-35 group.
B13: ="6. Research channel: "&Buying_Behaviour!F38&" leads for 18-25 buyers, while "&Buying_Behaviour!F42&" leads for the Above 55 group." -> 6. Research channel: Word of Mouth leads for 18-25 buyers, while Website leads for the Above 55 group.
B14: ="7. Complaints are spread out: the largest, "&Service_Experience!A22&", is only "&TEXT(Service_Experience!D22,"0.0%")&" of the total, and the top four reach "&TEXT(Service_Experience!E25,"0.0%")&"." -> 7. Complaints are spread out: the largest, Panel gaps, is only 17.8% of the total, and the top four reach 65.2%.
B15: ="8. Highway/Long Distance buyers choose automatic "&TEXT(Powertrain_Transmission!E55,"0.0%")&" of the time versus "&TEXT(Powertrain_Transmission!E54,"0.0%")&" for City Commute, but purpose and model tier overlap (see Powertrain_Transmission)." -> 8. Highway/Long Distance buyers choose automatic 85.2% of the time versus 38.3% for City Commute, but purpose and model tier overlap (see Powertrain_Transmission).
B17: Read with care
B18: - Convenience sample of 135 respondents in Hyderabad: results are directional, not market-wide.
B19: - Dealer, complaint and service-information patterns are unusually clean; treat dealer-level results as indicative.
B20: - Model tiers and life-stage segments are analyst groupings (defined in the Data sheet and Notes).

Sheet Demand_Profile
A1: Demand & Buyer Profile
A2: Which models draw interest, and who is interested in what. All figures are live formulas on the Data sheet.
A4: 1. Model demand
A5: Model | B5: Respondents | C5: % of total | D5: Rank
A6: Nexon | B6: =COUNTIF(Data!$H$2:$H$136,$A6) -> 35 | C6: =B6/COUNTA(Data!$A$2:$A$136) -> 0.25925926 | D6: =RANK(B6,$B$6:$B$11) -> 1
A7: Punch | B7: =COUNTIF(Data!$H$2:$H$136,$A7) -> 27 | C7: =B7/COUNTA(Data!$A$2:$A$136) -> 0.2 | D7: =RANK(B7,$B$6:$B$11) -> 2
A8: Safari | B8: =COUNTIF(Data!$H$2:$H$136,$A8) -> 23 | C8: =B8/COUNTA(Data!$A$2:$A$136) -> 0.17037037 | D8: =RANK(B8,$B$6:$B$11) -> 3
A9: Curvv | B9: =COUNTIF(Data!$H$2:$H$136,$A9) -> 19 | C9: =B9/COUNTA(Data!$A$2:$A$136) -> 0.14074074 | D9: =RANK(B9,$B$6:$B$11) -> 4
A10: Harrier | B10: =COUNTIF(Data!$H$2:$H$136,$A10) -> 16 | C10: =B10/COUNTA(Data!$A$2:$A$136) -> 0.11851852 | D10: =RANK(B10,$B$6:$B$11) -> 5
A11: Sierra | B11: =COUNTIF(Data!$H$2:$H$136,$A11) -> 15 | C11: =B11/COUNTA(Data!$A$2:$A$136) -> 0.11111111 | D11: =RANK(B11,$B$6:$B$11) -> 6
A12: Total | B12: =SUM(B6:B11) -> 135 | C12: =SUM(C6:C11) -> 1
A20: 2. Model interest by age group (respondents)
A21: Age group | B21: Nexon | C21: Punch | D21: Safari | E21: Curvv | F21: Harrier | G21: Sierra | H21: Total | I21: Top model
A22: 18-25 | B22: =COUNTIFS(Data!$C$2:$C$136,$A22,Data!$H$2:$H$136,B$21) -> 6 | C22: =COUNTIFS(Data!$C$2:$C$136,$A22,Data!$H$2:$H$136,C$21) -> 16 | D22: =COUNTIFS(Data!$C$2:$C$136,$A22,Data!$H$2:$H$136,D$21) -> 1 | E22: =COUNTIFS(Data!$C$2:$C$136,$A22,Data!$H$2:$H$136,E$21) -> 6 | F22: =COUNTIFS(Data!$C$2:$C$136,$A22,Data!$H$2:$H$136,F$21) -> 0 | G22: =COUNTIFS(Data!$C$2:$C$136,$A22,Data!$H$2:$H$136,G$21) -> 2 | H22: =SUM(B22:G22) -> 31 | I22: =INDEX($B$21:$G$21,MATCH(MAX(B22:G22),B22:G22,0)) -> Punch
A23: 26-35 | B23: =COUNTIFS(Data!$C$2:$C$136,$A23,Data!$H$2:$H$136,B$21) -> 20 | C23: =COUNTIFS(Data!$C$2:$C$136,$A23,Data!$H$2:$H$136,C$21) -> 4 | D23: =COUNTIFS(Data!$C$2:$C$136,$A23,Data!$H$2:$H$136,D$21) -> 0 | E23: =COUNTIFS(Data!$C$2:$C$136,$A23,Data!$H$2:$H$136,E$21) -> 7 | F23: =COUNTIFS(Data!$C$2:$C$136,$A23,Data!$H$2:$H$136,F$21) -> 3 | G23: =COUNTIFS(Data!$C$2:$C$136,$A23,Data!$H$2:$H$136,G$21) -> 8 | H23: =SUM(B23:G23) -> 42 | I23: =INDEX($B$21:$G$21,MATCH(MAX(B23:G23),B23:G23,0)) -> Nexon
A24: 36-45 | B24: =COUNTIFS(Data!$C$2:$C$136,$A24,Data!$H$2:$H$136,B$21) -> 0 | C24: =COUNTIFS(Data!$C$2:$C$136,$A24,Data!$H$2:$H$136,C$21) -> 5 | D24: =COUNTIFS(Data!$C$2:$C$136,$A24,Data!$H$2:$H$136,D$21) -> 11 | E24: =COUNTIFS(Data!$C$2:$C$136,$A24,Data!$H$2:$H$136,E$21) -> 0 | F24: =COUNTIFS(Data!$C$2:$C$136,$A24,Data!$H$2:$H$136,F$21) -> 6 | G24: =COUNTIFS(Data!$C$2:$C$136,$A24,Data!$H$2:$H$136,G$21) -> 5 | H24: =SUM(B24:G24) -> 27 | I24: =INDEX($B$21:$G$21,MATCH(MAX(B24:G24),B24:G24,0)) -> Safari
A25: 46-55 | B25: =COUNTIFS(Data!$C$2:$C$136,$A25,Data!$H$2:$H$136,B$21) -> 3 | C25: =COUNTIFS(Data!$C$2:$C$136,$A25,Data!$H$2:$H$136,C$21) -> 0 | D25: =COUNTIFS(Data!$C$2:$C$136,$A25,Data!$H$2:$H$136,D$21) -> 6 | E25: =COUNTIFS(Data!$C$2:$C$136,$A25,Data!$H$2:$H$136,E$21) -> 3 | F25: =COUNTIFS(Data!$C$2:$C$136,$A25,Data!$H$2:$H$136,F$21) -> 7 | G25: =COUNTIFS(Data!$C$2:$C$136,$A25,Data!$H$2:$H$136,G$21) -> 0 | H25: =SUM(B25:G25) -> 19 | I25: =INDEX($B$21:$G$21,MATCH(MAX(B25:G25),B25:G25,0)) -> Harrier
A26: Above 55 | B26: =COUNTIFS(Data!$C$2:$C$136,$A26,Data!$H$2:$H$136,B$21) -> 6 | C26: =COUNTIFS(Data!$C$2:$C$136,$A26,Data!$H$2:$H$136,C$21) -> 2 | D26: =COUNTIFS(Data!$C$2:$C$136,$A26,Data!$H$2:$H$136,D$21) -> 5 | E26: =COUNTIFS(Data!$C$2:$C$136,$A26,Data!$H$2:$H$136,E$21) -> 3 | F26: =COUNTIFS(Data!$C$2:$C$136,$A26,Data!$H$2:$H$136,F$21) -> 0 | G26: =COUNTIFS(Data!$C$2:$C$136,$A26,Data!$H$2:$H$136,G$21) -> 0 | H26: =SUM(B26:G26) -> 16 | I26: =INDEX($B$21:$G$21,MATCH(MAX(B26:G26),B26:G26,0)) -> Nexon
A36: 3. Model tier by income band (% of band)
A37: Income band | B37: Entry | C37: Compact | D37: Premium | E37: Respondents
A38: Below 50K | B38: =COUNTIFS(Data!$F$2:$F$136,$A38,Data!$AC$2:$AC$136,B$37)/$E38 -> 0.36842105 | C38: =COUNTIFS(Data!$F$2:$F$136,$A38,Data!$AC$2:$AC$136,C$37)/$E38 -> 0.21052632 | D38: =COUNTIFS(Data!$F$2:$F$136,$A38,Data!$AC$2:$AC$136,D$37)/$E38 -> 0.42105263 | E38: =COUNTIF(Data!$F$2:$F$136,$A38) -> 19
A39: 50K-1L | B39: =COUNTIFS(Data!$F$2:$F$136,$A39,Data!$AC$2:$AC$136,B$37)/$E39 -> 0.20512821 | C39: =COUNTIFS(Data!$F$2:$F$136,$A39,Data!$AC$2:$AC$136,C$37)/$E39 -> 0.56410256 | D39: =COUNTIFS(Data!$F$2:$F$136,$A39,Data!$AC$2:$AC$136,D$37)/$E39 -> 0.23076923 | E39: =COUNTIF(Data!$F$2:$F$136,$A39) -> 39
A40: 1L-2L | B40: =COUNTIFS(Data!$F$2:$F$136,$A40,Data!$AC$2:$AC$136,B$37)/$E40 -> 0.19565217 | C40: =COUNTIFS(Data!$F$2:$F$136,$A40,Data!$AC$2:$AC$136,C$37)/$E40 -> 0.45652174 | D40: =COUNTIFS(Data!$F$2:$F$136,$A40,Data!$AC$2:$AC$136,D$37)/$E40 -> 0.34782609 | E40: =COUNTIF(Data!$F$2:$F$136,$A40) -> 46
A41: Above 2L | B41: =COUNTIFS(Data!$F$2:$F$136,$A41,Data!$AC$2:$AC$136,B$37)/$E41 -> 0.096774194 | C41: =COUNTIFS(Data!$F$2:$F$136,$A41,Data!$AC$2:$AC$136,C$37)/$E41 -> 0.22580645 | D41: =COUNTIFS(Data!$F$2:$F$136,$A41,Data!$AC$2:$AC$136,D$37)/$E41 -> 0.67741935 | E41: =COUNTIF(Data!$F$2:$F$136,$A41) -> 31
A43: Tiers are an analyst grouping: Entry = Punch; Compact = Nexon, Curvv; Premium = Harrier, Safari, Sierra.

Sheet Powertrain_Transmission
A1: Powertrain & Transmission
A2: EV, fuel and automatic-transmission preferences by segment.
A4: 1. EV share by age group
A5: Age group | B5: Respondents | C5: EV choosers | D5: EV %
A6: 18-25 | B6: =COUNTIF(Data!$C$2:$C$136,$A6) -> 31 | C6: =COUNTIFS(Data!$C$2:$C$136,$A6,Data!$I$2:$I$136,"EV") -> 7 | D6: =C6/B6 -> 0.22580645
A7: 26-35 | B7: =COUNTIF(Data!$C$2:$C$136,$A7) -> 42 | C7: =COUNTIFS(Data!$C$2:$C$136,$A7,Data!$I$2:$I$136,"EV") -> 21 | D7: =C7/B7 -> 0.5
A8: 36-45 | B8: =COUNTIF(Data!$C$2:$C$136,$A8) -> 27 | C8: =COUNTIFS(Data!$C$2:$C$136,$A8,Data!$I$2:$I$136,"EV") -> 4 | D8: =C8/B8 -> 0.14814815
A9: 46-55 | B9: =COUNTIF(Data!$C$2:$C$136,$A9) -> 19 | C9: =COUNTIFS(Data!$C$2:$C$136,$A9,Data!$I$2:$I$136,"EV") -> 3 | D9: =C9/B9 -> 0.15789474
A10: Above 55 | B10: =COUNTIF(Data!$C$2:$C$136,$A10) -> 16 | C10: =COUNTIFS(Data!$C$2:$C$136,$A10,Data!$I$2:$I$136,"EV") -> 7 | D10: =C10/B10 -> 0.4375
A20: 2. EV share by income band
A21: Income band | B21: Respondents | C21: EV choosers | D21: EV %
A22: Below 50K | B22: =COUNTIF(Data!$F$2:$F$136,$A22) -> 19 | C22: =COUNTIFS(Data!$F$2:$F$136,$A22,Data!$I$2:$I$136,"EV") -> 3 | D22: =C22/B22 -> 0.15789474
A23: 50K-1L | B23: =COUNTIF(Data!$F$2:$F$136,$A23) -> 39 | C23: =COUNTIFS(Data!$F$2:$F$136,$A23,Data!$I$2:$I$136,"EV") -> 16 | D23: =C23/B23 -> 0.41025641
A24: 1L-2L | B24: =COUNTIF(Data!$F$2:$F$136,$A24) -> 46 | C24: =COUNTIFS(Data!$F$2:$F$136,$A24,Data!$I$2:$I$136,"EV") -> 14 | D24: =C24/B24 -> 0.30434783
A25: Above 2L | B25: =COUNTIF(Data!$F$2:$F$136,$A25) -> 31 | C25: =COUNTIFS(Data!$F$2:$F$136,$A25,Data!$I$2:$I$136,"EV") -> 9 | D25: =C25/B25 -> 0.29032258
A36: 3. Powertrain by model (respondents)
A37: Model | B37: EV | C37: Petrol | D37: Diesel | E37: CNG | F37: Total | G37: EV %
A38: Nexon | B38: =COUNTIFS(Data!$H$2:$H$136,$A38,Data!$I$2:$I$136,B$37) -> 22 | C38: =COUNTIFS(Data!$H$2:$H$136,$A38,Data!$I$2:$I$136,C$37) -> 7 | D38: =COUNTIFS(Data!$H$2:$H$136,$A38,Data!$I$2:$I$136,D$37) -> 4 | E38: =COUNTIFS(Data!$H$2:$H$136,$A38,Data!$I$2:$I$136,E$37) -> 2 | F38: =SUM(B38:E38) -> 35 | G38: =B38/F38 -> 0.62857143
A39: Punch | B39: =COUNTIFS(Data!$H$2:$H$136,$A39,Data!$I$2:$I$136,B$37) -> 3 | C39: =COUNTIFS(Data!$H$2:$H$136,$A39,Data!$I$2:$I$136,C$37) -> 15 | D39: =COUNTIFS(Data!$H$2:$H$136,$A39,Data!$I$2:$I$136,D$37) -> 5 | E39: =COUNTIFS(Data!$H$2:$H$136,$A39,Data!$I$2:$I$136,E$37) -> 4 | F39: =SUM(B39:E39) -> 27 | G39: =B39/F39 -> 0.11111111
A40: Safari | B40: =COUNTIFS(Data!$H$2:$H$136,$A40,Data!$I$2:$I$136,B$37) -> 3 | C40: =COUNTIFS(Data!$H$2:$H$136,$A40,Data!$I$2:$I$136,C$37) -> 5 | D40: =COUNTIFS(Data!$H$2:$H$136,$A40,Data!$I$2:$I$136,D$37) -> 13 | E40: =COUNTIFS(Data!$H$2:$H$136,$A40,Data!$I$2:$I$136,E$37) -> 2 | F40: =SUM(B40:E40) -> 23 | G40: =B40/F40 -> 0.13043478
A41: Curvv | B41: =COUNTIFS(Data!$H$2:$H$136,$A41,Data!$I$2:$I$136,B$37) -> 7 | C41: =COUNTIFS(Data!$H$2:$H$136,$A41,Data!$I$2:$I$136,C$37) -> 4 | D41: =COUNTIFS(Data!$H$2:$H$136,$A41,Data!$I$2:$I$136,D$37) -> 2 | E41: =COUNTIFS(Data!$H$2:$H$136,$A41,Data!$I$2:$I$136,E$37) -> 6 | F41: =SUM(B41:E41) -> 19 | G41: =B41/F41 -> 0.36842105
A42: Harrier | B42: =COUNTIFS(Data!$H$2:$H$136,$A42,Data!$I$2:$I$136,B$37) -> 2 | C42: =COUNTIFS(Data!$H$2:$H$136,$A42,Data!$I$2:$I$136,C$37) -> 2 | D42: =COUNTIFS(Data!$H$2:$H$136,$A42,Data!$I$2:$I$136,D$37) -> 9 | E42: =COUNTIFS(Data!$H$2:$H$136,$A42,Data!$I$2:$I$136,E$37) -> 3 | F42: =SUM(B42:E42) -> 16 | G42: =B42/F42 -> 0.125
A43: Sierra | B43: =COUNTIFS(Data!$H$2:$H$136,$A43,Data!$I$2:$I$136,B$37) -> 5 | C43: =COUNTIFS(Data!$H$2:$H$136,$A43,Data!$I$2:$I$136,C$37) -> 2 | D43: =COUNTIFS(Data!$H$2:$H$136,$A43,Data!$I$2:$I$136,D$37) -> 6 | E43: =COUNTIFS(Data!$H$2:$H$136,$A43,Data!$I$2:$I$136,E$37) -> 2 | F43: =SUM(B43:E43) -> 15 | G43: =B43/F43 -> 0.33333333
A52: 4. Automatic transmission share
A53: Dimension | B53: Segment | C53: Respondents | D53: Automatic | E53: Automatic %
A54: Purpose | B54: City Commute | C54: =COUNTIF(Data!$M$2:$M$136,$B54) -> 81 | D54: =COUNTIFS(Data!$M$2:$M$136,$B54,Data!$J$2:$J$136,"Automatic") -> 31 | E54: =D54/C54 -> 0.38271605
A55: Purpose | B55: Highway/Long Distance | C55: =COUNTIF(Data!$M$2:$M$136,$B55) -> 54 | D55: =COUNTIFS(Data!$M$2:$M$136,$B55,Data!$J$2:$J$136,"Automatic") -> 46 | E55: =D55/C55 -> 0.85185185
A56: Age group | B56: 18-25 | C56: =COUNTIF(Data!$C$2:$C$136,$B56) -> 31 | D56: =COUNTIFS(Data!$C$2:$C$136,$B56,Data!$J$2:$J$136,"Automatic") -> 14 | E56: =D56/C56 -> 0.4516129
A57: Age group | B57: 26-35 | C57: =COUNTIF(Data!$C$2:$C$136,$B57) -> 42 | D57: =COUNTIFS(Data!$C$2:$C$136,$B57,Data!$J$2:$J$136,"Automatic") -> 19 | E57: =D57/C57 -> 0.45238095
A58: Age group | B58: 36-45 | C58: =COUNTIF(Data!$C$2:$C$136,$B58) -> 27 | D58: =COUNTIFS(Data!$C$2:$C$136,$B58,Data!$J$2:$J$136,"Automatic") -> 19 | E58: =D58/C58 -> 0.7037037
A59: Age group | B59: 46-55 | C59: =COUNTIF(Data!$C$2:$C$136,$B59) -> 19 | D59: =COUNTIFS(Data!$C$2:$C$136,$B59,Data!$J$2:$J$136,"Automatic") -> 15 | E59: =D59/C59 -> 0.78947368
A60: Age group | B60: Above 55 | C60: =COUNTIF(Data!$C$2:$C$136,$B60) -> 16 | D60: =COUNTIFS(Data!$C$2:$C$136,$B60,Data!$J$2:$J$136,"Automatic") -> 10 | E60: =D60/C60 -> 0.625
A62: Overlap check: Highway/Long Distance buyers who chose a Premium-tier model | E62: =COUNTIFS(Data!$M$2:$M$136,"Highway/Long Distance",Data!$AC$2:$AC$136,"Premium") -> 54
A63: Highway/Long Distance buyers in total | E63: =COUNTIF(Data!$M$2:$M$136,"Highway/Long Distance") -> 54
A64: If these two numbers are equal, purpose and model tier overlap completely, so the effect of purpose cannot be separated from the effect of model.

Sheet Buying_Behaviour
A1: Buying Behaviour
A2: Payment modes and research channels by segment.
A4: 1. Payment mode by income band
A5: Income band | B5: Respondents | C5: Loan | D5: Digital | E5: Cheque | F5: Loan %
A6: Below 50K | B6: =COUNTIF(Data!$F$2:$F$136,$A6) -> 19 | C6: =COUNTIFS(Data!$F$2:$F$136,$A6,Data!$S$2:$S$136,C$5) -> 14 | D6: =COUNTIFS(Data!$F$2:$F$136,$A6,Data!$S$2:$S$136,D$5) -> 3 | E6: =COUNTIFS(Data!$F$2:$F$136,$A6,Data!$S$2:$S$136,E$5) -> 2 | F6: =C6/B6 -> 0.73684211
A7: 50K-1L | B7: =COUNTIF(Data!$F$2:$F$136,$A7) -> 39 | C7: =COUNTIFS(Data!$F$2:$F$136,$A7,Data!$S$2:$S$136,C$5) -> 33 | D7: =COUNTIFS(Data!$F$2:$F$136,$A7,Data!$S$2:$S$136,D$5) -> 2 | E7: =COUNTIFS(Data!$F$2:$F$136,$A7,Data!$S$2:$S$136,E$5) -> 4 | F7: =C7/B7 -> 0.84615385
A8: 1L-2L | B8: =COUNTIF(Data!$F$2:$F$136,$A8) -> 46 | C8: =COUNTIFS(Data!$F$2:$F$136,$A8,Data!$S$2:$S$136,C$5) -> 31 | D8: =COUNTIFS(Data!$F$2:$F$136,$A8,Data!$S$2:$S$136,D$5) -> 9 | E8: =COUNTIFS(Data!$F$2:$F$136,$A8,Data!$S$2:$S$136,E$5) -> 6 | F8: =C8/B8 -> 0.67391304
A9: Above 2L | B9: =COUNTIF(Data!$F$2:$F$136,$A9) -> 31 | C9: =COUNTIFS(Data!$F$2:$F$136,$A9,Data!$S$2:$S$136,C$5) -> 22 | D9: =COUNTIFS(Data!$F$2:$F$136,$A9,Data!$S$2:$S$136,D$5) -> 5 | E9: =COUNTIFS(Data!$F$2:$F$136,$A9,Data!$S$2:$S$136,E$5) -> 4 | F9: =C9/B9 -> 0.70967742
A20: 2. Payment mode by age group
A21: Age group | B21: Respondents | C21: Loan | D21: Digital | E21: Cheque | F21: Loan %
A22: 18-25 | B22: =COUNTIF(Data!$C$2:$C$136,$A22) -> 31 | C22: =COUNTIFS(Data!$C$2:$C$136,$A22,Data!$S$2:$S$136,C$21) -> 22 | D22: =COUNTIFS(Data!$C$2:$C$136,$A22,Data!$S$2:$S$136,D$21) -> 9 | E22: =COUNTIFS(Data!$C$2:$C$136,$A22,Data!$S$2:$S$136,E$21) -> 0 | F22: =C22/B22 -> 0.70967742
A23: 26-35 | B23: =COUNTIF(Data!$C$2:$C$136,$A23) -> 42 | C23: =COUNTIFS(Data!$C$2:$C$136,$A23,Data!$S$2:$S$136,C$21) -> 36 | D23: =COUNTIFS(Data!$C$2:$C$136,$A23,Data!$S$2:$S$136,D$21) -> 5 | E23: =COUNTIFS(Data!$C$2:$C$136,$A23,Data!$S$2:$S$136,E$21) -> 1 | F23: =C23/B23 -> 0.85714286
A24: 36-45 | B24: =COUNTIF(Data!$C$2:$C$136,$A24) -> 27 | C24: =COUNTIFS(Data!$C$2:$C$136,$A24,Data!$S$2:$S$136,C$21) -> 22 | D24: =COUNTIFS(Data!$C$2:$C$136,$A24,Data!$S$2:$S$136,D$21) -> 5 | E24: =COUNTIFS(Data!$C$2:$C$136,$A24,Data!$S$2:$S$136,E$21) -> 0 | F24: =C24/B24 -> 0.81481481
A25: 46-55 | B25: =COUNTIF(Data!$C$2:$C$136,$A25) -> 19 | C25: =COUNTIFS(Data!$C$2:$C$136,$A25,Data!$S$2:$S$136,C$21) -> 11 | D25: =COUNTIFS(Data!$C$2:$C$136,$A25,Data!$S$2:$S$136,D$21) -> 0 | E25: =COUNTIFS(Data!$C$2:$C$136,$A25,Data!$S$2:$S$136,E$21) -> 8 | F25: =C25/B25 -> 0.57894737
A26: Above 55 | B26: =COUNTIF(Data!$C$2:$C$136,$A26) -> 16 | C26: =COUNTIFS(Data!$C$2:$C$136,$A26,Data!$S$2:$S$136,C$21) -> 9 | D26: =COUNTIFS(Data!$C$2:$C$136,$A26,Data!$S$2:$S$136,D$21) -> 0 | E26: =COUNTIFS(Data!$C$2:$C$136,$A26,Data!$S$2:$S$136,E$21) -> 7 | F26: =C26/B26 -> 0.5625
A36: 3. Research channel by age group
A37: Age group | B37: Respondents | C37: Website | D37: YouTube | E37: Word of Mouth | F37: Top channel
A38: 18-25 | B38: =COUNTIF(Data!$C$2:$C$136,$A38) -> 31 | C38: =COUNTIFS(Data!$C$2:$C$136,$A38,Data!$R$2:$R$136,C$37) -> 10 | D38: =COUNTIFS(Data!$C$2:$C$136,$A38,Data!$R$2:$R$136,D$37) -> 8 | E38: =COUNTIFS(Data!$C$2:$C$136,$A38,Data!$R$2:$R$136,E$37) -> 13 | F38: =INDEX($C$37:$E$37,MATCH(MAX(C38:E38),C38:E38,0)) -> Word of Mouth
A39: 26-35 | B39: =COUNTIF(Data!$C$2:$C$136,$A39) -> 42 | C39: =COUNTIFS(Data!$C$2:$C$136,$A39,Data!$R$2:$R$136,C$37) -> 14 | D39: =COUNTIFS(Data!$C$2:$C$136,$A39,Data!$R$2:$R$136,D$37) -> 12 | E39: =COUNTIFS(Data!$C$2:$C$136,$A39,Data!$R$2:$R$136,E$37) -> 16 | F39: =INDEX($C$37:$E$37,MATCH(MAX(C39:E39),C39:E39,0)) -> Word of Mouth
A40: 36-45 | B40: =COUNTIF(Data!$C$2:$C$136,$A40) -> 27 | C40: =COUNTIFS(Data!$C$2:$C$136,$A40,Data!$R$2:$R$136,C$37) -> 8 | D40: =COUNTIFS(Data!$C$2:$C$136,$A40,Data!$R$2:$R$136,D$37) -> 7 | E40: =COUNTIFS(Data!$C$2:$C$136,$A40,Data!$R$2:$R$136,E$37) -> 12 | F40: =INDEX($C$37:$E$37,MATCH(MAX(C40:E40),C40:E40,0)) -> Word of Mouth
A41: 46-55 | B41: =COUNTIF(Data!$C$2:$C$136,$A41) -> 19 | C41: =COUNTIFS(Data!$C$2:$C$136,$A41,Data!$R$2:$R$136,C$37) -> 10 | D41: =COUNTIFS(Data!$C$2:$C$136,$A41,Data!$R$2:$R$136,D$37) -> 6 | E41: =COUNTIFS(Data!$C$2:$C$136,$A41,Data!$R$2:$R$136,E$37) -> 3 | F41: =INDEX($C$37:$E$37,MATCH(MAX(C41:E41),C41:E41,0)) -> Website
A42: Above 55 | B42: =COUNTIF(Data!$C$2:$C$136,$A42) -> 16 | C42: =COUNTIFS(Data!$C$2:$C$136,$A42,Data!$R$2:$R$136,C$37) -> 8 | D42: =COUNTIFS(Data!$C$2:$C$136,$A42,Data!$R$2:$R$136,D$37) -> 5 | E42: =COUNTIFS(Data!$C$2:$C$136,$A42,Data!$R$2:$R$136,E$37) -> 3 | F42: =INDEX($C$37:$E$37,MATCH(MAX(C42:E42),C42:E42,0)) -> Website

Sheet Service_Experience
A1: Service & Ownership Experience
A2: Complaint themes by dealer, complaint ranking, and service-information awareness.
A4: 1. Complaint theme by dealer
A5: Dealer | B5: Respondents | C5: Software | D5: Service | E5: Fit & Finish | F5: Software % | G5: Service % | H5: Fit & Finish %
A6: Tejaswi Motors | B6: =COUNTIF(Data!$U$2:$U$136,$A6) -> 58 | C6: =COUNTIFS(Data!$U$2:$U$136,$A6,Data!$AB$2:$AB$136,"Software Instability") -> 36 | D6: =COUNTIFS(Data!$U$2:$U$136,$A6,Data!$AB$2:$AB$136,"Service Competence & Capacity") -> 22 | E6: =COUNTIFS(Data!$U$2:$U$136,$A6,Data!$AB$2:$AB$136,"Fit & Finish") -> 0 | F6: =C6/$B6 -> 0.62068966 | G6: =D6/$B6 -> 0.37931034 | H6: =E6/$B6 -> 0
A7: Select Cars | B7: =COUNTIF(Data!$U$2:$U$136,$A7) -> 42 | C7: =COUNTIFS(Data!$U$2:$U$136,$A7,Data!$AB$2:$AB$136,"Software Instability") -> 0 | D7: =COUNTIFS(Data!$U$2:$U$136,$A7,Data!$AB$2:$AB$136,"Service Competence & Capacity") -> 18 | E7: =COUNTIFS(Data!$U$2:$U$136,$A7,Data!$AB$2:$AB$136,"Fit & Finish") -> 24 | F7: =C7/$B7 -> 0 | G7: =D7/$B7 -> 0.42857143 | H7: =E7/$B7 -> 0.57142857
A8: Venkataramana Motors | B8: =COUNTIF(Data!$U$2:$U$136,$A8) -> 35 | C8: =COUNTIFS(Data!$U$2:$U$136,$A8,Data!$AB$2:$AB$136,"Software Instability") -> 0 | D8: =COUNTIFS(Data!$U$2:$U$136,$A8,Data!$AB$2:$AB$136,"Service Competence & Capacity") -> 0 | E8: =COUNTIFS(Data!$U$2:$U$136,$A8,Data!$AB$2:$AB$136,"Fit & Finish") -> 35 | F8: =C8/$B8 -> 0 | G8: =D8/$B8 -> 0 | H8: =E8/$B8 -> 1
A9: Themes: Software = software stability + infotainment lag; Service = service response + parts availability; Fit & Finish = panel gaps + plastic quality + fit and finish.
A20: 2. Complaint ranking (Pareto)
A21: Complaint | B21: Theme | C21: Respondents | D21: % of total | E21: Cumulative %
A22: Panel gaps | B22: Fit & Finish | C22: =COUNTIF(Data!$AA$2:$AA$136,$A22) -> 24 | D22: =C22/COUNTA(Data!$A$2:$A$136) -> 0.17777778 | E22: =SUM($D$22:D22) -> 0.17777778
A23: Service response | B23: Service Competence & Capacity | C23: =COUNTIF(Data!$AA$2:$AA$136,$A23) -> 22 | D23: =C23/COUNTA(Data!$A$2:$A$136) -> 0.16296296 | E23: =SUM($D$22:D23) -> 0.34074074
A24: Software stability | B24: Software Instability | C24: =COUNTIF(Data!$AA$2:$AA$136,$A24) -> 22 | D24: =C24/COUNTA(Data!$A$2:$A$136) -> 0.16296296 | E24: =SUM($D$22:D24) -> 0.5037037
A25: Plastic quality | B25: Fit & Finish | C25: =COUNTIF(Data!$AA$2:$AA$136,$A25) -> 20 | D25: =C25/COUNTA(Data!$A$2:$A$136) -> 0.14814815 | E25: =SUM($D$22:D25) -> 0.65185185
A26: Parts availability | B26: Service Competence & Capacity | C26: =COUNTIF(Data!$AA$2:$AA$136,$A26) -> 18 | D26: =C26/COUNTA(Data!$A$2:$A$136) -> 0.13333333 | E26: =SUM($D$22:D26) -> 0.78518519
A27: Fit and finish | B27: Fit & Finish | C27: =COUNTIF(Data!$AA$2:$AA$136,$A27) -> 15 | D27: =C27/COUNTA(Data!$A$2:$A$136) -> 0.11111111 | E27: =SUM($D$22:D27) -> 0.8962963
A28: Infotainment lag | B28: Software Instability | C28: =COUNTIF(Data!$AA$2:$AA$136,$A28) -> 14 | D28: =C28/COUNTA(Data!$A$2:$A$136) -> 0.1037037 | E28: =SUM($D$22:D28) -> 1
A29: Total | C29: =SUM(C22:C28) -> 135 | D29: =SUM(D22:D28) -> 1
A34: 3. Respondents with no service information (brand trust)
A35: Dealer | B35: Respondents | C35: No service info | D35: % of dealer
A36: Tejaswi Motors | B36: =COUNTIF(Data!$U$2:$U$136,$A36) -> 58 | C36: =COUNTIFS(Data!$U$2:$U$136,$A36,Data!$Y$2:$Y$136,"No") -> 0 | D36: =C36/B36 -> 0
A37: Select Cars | B37: =COUNTIF(Data!$U$2:$U$136,$A37) -> 42 | C37: =COUNTIFS(Data!$U$2:$U$136,$A37,Data!$Y$2:$Y$136,"No") -> 21 | D37: =C37/B37 -> 0.5
A38: Venkataramana Motors | B38: =COUNTIF(Data!$U$2:$U$136,$A38) -> 35 | C38: =COUNTIFS(Data!$U$2:$U$136,$A38,Data!$Y$2:$Y$136,"No") -> 0 | D38: =C38/B38 -> 0

Sheet Segment_Scorecard
A1: Segment Scorecard
A2: Five life-stage segments (defined by age group) compared on the main behaviours. Colour scale runs within each column.
A4: Life-stage segments
A5: Segment | B5: Respondents | C5: % of total | D5: EV % | E5: Automatic % | F5: Loan % | G5: Premium % | H5: Avg budget index
A6: Gen Z (18-25) | B6: =COUNTIF(Data!$AD$2:$AD$136,$A6) -> 31 | C6: =B6/COUNTA(Data!$A$2:$A$136) -> 0.22962963 | D6: =COUNTIFS(Data!$AD$2:$AD$136,$A6,Data!$I$2:$I$136,"EV")/$B6 -> 0.22580645 | E6: =COUNTIFS(Data!$AD$2:$AD$136,$A6,Data!$J$2:$J$136,"Automatic")/$B6 -> 0.4516129 | F6: =COUNTIFS(Data!$AD$2:$AD$136,$A6,Data!$S$2:$S$136,"Loan")/$B6 -> 0.70967742 | G6: =COUNTIFS(Data!$AD$2:$AD$136,$A6,Data!$AC$2:$AC$136,"Premium")/$B6 -> 0.096774194 | H6: =AVERAGEIFS(Data!$L$2:$L$136,Data!$AD$2:$AD$136,$A6) -> 2.483871
A7: Young professionals (26-35) | B7: =COUNTIF(Data!$AD$2:$AD$136,$A7) -> 42 | C7: =B7/COUNTA(Data!$A$2:$A$136) -> 0.31111111 | D7: =COUNTIFS(Data!$AD$2:$AD$136,$A7,Data!$I$2:$I$136,"EV")/$B7 -> 0.5 | E7: =COUNTIFS(Data!$AD$2:$AD$136,$A7,Data!$J$2:$J$136,"Automatic")/$B7 -> 0.45238095 | F7: =COUNTIFS(Data!$AD$2:$AD$136,$A7,Data!$S$2:$S$136,"Loan")/$B7 -> 0.85714286 | G7: =COUNTIFS(Data!$AD$2:$AD$136,$A7,Data!$AC$2:$AC$136,"Premium")/$B7 -> 0.26190476 | H7: =AVERAGEIFS(Data!$L$2:$L$136,Data!$AD$2:$AD$136,$A7) -> 2.8571429
A8: Family builders (36-45) | B8: =COUNTIF(Data!$AD$2:$AD$136,$A8) -> 27 | C8: =B8/COUNTA(Data!$A$2:$A$136) -> 0.2 | D8: =COUNTIFS(Data!$AD$2:$AD$136,$A8,Data!$I$2:$I$136,"EV")/$B8 -> 0.14814815 | E8: =COUNTIFS(Data!$AD$2:$AD$136,$A8,Data!$J$2:$J$136,"Automatic")/$B8 -> 0.7037037 | F8: =COUNTIFS(Data!$AD$2:$AD$136,$A8,Data!$S$2:$S$136,"Loan")/$B8 -> 0.81481481 | G8: =COUNTIFS(Data!$AD$2:$AD$136,$A8,Data!$AC$2:$AC$136,"Premium")/$B8 -> 0.81481481 | H8: =AVERAGEIFS(Data!$L$2:$L$136,Data!$AD$2:$AD$136,$A8) -> 2.7407407
A9: Pre-retirement (46-55) | B9: =COUNTIF(Data!$AD$2:$AD$136,$A9) -> 19 | C9: =B9/COUNTA(Data!$A$2:$A$136) -> 0.14074074 | D9: =COUNTIFS(Data!$AD$2:$AD$136,$A9,Data!$I$2:$I$136,"EV")/$B9 -> 0.15789474 | E9: =COUNTIFS(Data!$AD$2:$AD$136,$A9,Data!$J$2:$J$136,"Automatic")/$B9 -> 0.78947368 | F9: =COUNTIFS(Data!$AD$2:$AD$136,$A9,Data!$S$2:$S$136,"Loan")/$B9 -> 0.57894737 | G9: =COUNTIFS(Data!$AD$2:$AD$136,$A9,Data!$AC$2:$AC$136,"Premium")/$B9 -> 0.68421053 | H9: =AVERAGEIFS(Data!$L$2:$L$136,Data!$AD$2:$AD$136,$A9) -> 2.8947368
A10: Seniors (55+) | B10: =COUNTIF(Data!$AD$2:$AD$136,$A10) -> 16 | C10: =B10/COUNTA(Data!$A$2:$A$136) -> 0.11851852 | D10: =COUNTIFS(Data!$AD$2:$AD$136,$A10,Data!$I$2:$I$136,"EV")/$B10 -> 0.4375 | E10: =COUNTIFS(Data!$AD$2:$AD$136,$A10,Data!$J$2:$J$136,"Automatic")/$B10 -> 0.625 | F10: =COUNTIFS(Data!$AD$2:$AD$136,$A10,Data!$S$2:$S$136,"Loan")/$B10 -> 0.5625 | G10: =COUNTIFS(Data!$AD$2:$AD$136,$A10,Data!$AC$2:$AC$136,"Premium")/$B10 -> 0.3125 | H10: =AVERAGEIFS(Data!$L$2:$L$136,Data!$AD$2:$AD$136,$A10) -> 2.8125
A12: Avg budget index: 1 = Below 10L, 2 = 10L-18L, 3 = 18L-25L, 4 = Above 25L (Budget_Sort in the Data sheet).
A13: Segments with fewer than about 30 respondents are indicative only.

Sheet Data
A1: Respondent_ID | B1: Gender | C1: Age_Group | D1: Age_Sort | E1: Occupation | F1: Income_Band | G1: Income_Sort | H1: Model_Interest | I1: Powertrain | J1: Transmission | K1: Budget_Band | L1: Budget_Sort | M1: Purpose | N1: Motivation_1 | O1: Motivation_2 | P1: Motivation_3 | Q1: Tech_Must_Have | R1: Info_Source | S1: Finance_Mode | T1: Purchase_Occasion | U1: Dealer | V1: Dealer_Area | W1: Dealer_Choice_Reason | X1: Resale_Expectation | Y1: Service_Info_Known | Z1: No_Info_Reason | AA1: Ownership_Complaint | AB1: Complaint_Theme | AC1: Model_Tier | AD1: Life_Stage
A2: 1 | B2: Female | C2: 18-25 | D2: 1 | E2: Salaried | F2: Below 50K | G2: 1 | H2: Punch | I2: Petrol | J2: Manual | K2: Below 10L | L2: 1 | M2: City Commute | N2: Safety | O2: Ground Clearance | P2: Budget | Q2: 360 Camera | R2: Word of Mouth | S2: Loan | T2: Festival | U2: Select Cars | V2: Moosapet | W2: Test Drive | X2: Yes | Y2: Yes | AA2: Parts availability | AB2: Service Competence & Capacity | AC2: =IF(H2="Punch","Entry",IF(OR(H2="Nexon",H2="Curvv"),"Compact","Premium")) -> Entry | AD2: =IF(C2="18-25","Gen Z (18-25)",IF(C2="26-35","Young professionals (26-35)",IF(C2="36-45","Family builders (36-45)",IF(C2="46-55","Pre-retirement (46-55)","Seniors (55+)")))) -> Gen Z (18-25)
A3: 2 | B3: Male | C3: 36-45 | D3: 3 | E3: Business | F3: Above 2L | G3: 4 | H3: Sierra | I3: Diesel | J3: Automatic | K3: Above 25L | L3: 4 | M3: Highway/Long Distance | N3: Safety | O3: Ground Clearance | P3: Budget | Q3: 360 Camera | R3: Website | S3: Loan | T3: Festival | U3: Tejaswi Motors | V3: Hi-Tech | W3: Proximity | X3: No | Y3: Yes | AA3: Software stability | AB3: Software Instability | AC3: =IF(H3="Punch","Entry",IF(OR(H3="Nexon",H3="Curvv"),"Compact","Premium")) -> Premium | AD3: =IF(C3="18-25","Gen Z (18-25)",IF(C3="26-35","Young professionals (26-35)",IF(C3="36-45","Family builders (36-45)",IF(C3="46-55","Pre-retirement (46-55)","Seniors (55+)")))) -> Family builders (36-45)
A4: 3 | B4: Male | C4: 26-35 | D4: 2 | E4: Salaried | F4: Above 2L | G4: 4 | H4: Nexon | I4: CNG | J4: Manual | K4: Above 25L | L4: 4 | M4: City Commute | N4: Safety | O4: Ground Clearance | P4: Budget | Q4: Sunroof | R4: Word of Mouth | S4: Digital | T4: Birthday | U4: Select Cars | V4: Moosapet | W4: Test Drive | X4: Yes | Y4: Yes | AA4: Panel gaps | AB4: Fit & Finish | AC4: =IF(H4="Punch","Entry",IF(OR(H4="Nexon",H4="Curvv"),"Compact","Premium")) -> Compact | AD4: =IF(C4="18-25","Gen Z (18-25)",IF(C4="26-35","Young professionals (26-35)",IF(C4="36-45","Family builders (36-45)",IF(C4="46-55","Pre-retirement (46-55)","Seniors (55+)")))) -> Young professionals (26-35)
A5: 4 | B5: Male | C5: 18-25 | D5: 1 | E5: Salaried | F5: Above 2L | G5: 4 | H5: Curvv | I5: EV | J5: Automatic | K5: Above 25L | L5: 4 | M5: City Commute | N5: Safety | O5: Styling | P5: Tech | Q5: Acti.ev Tech | R5: Website | S5: Digital | T5: Festival | U5: Tejaswi Motors | V5: Hi-Tech | W5: Proximity | X5: No | Y5: Yes | AA5: Service response | AB5: Service Competence & Capacity | AC5: =IF(H5="Punch","Entry",IF(OR(H5="Nexon",H5="Curvv"),"Compact","Premium")) -> Compact | AD5: =IF(C5="18-25","Gen Z (18-25)",IF(C5="26-35","Young professionals (26-35)",IF(C5="36-45","Family builders (36-45)",IF(C5="46-55","Pre-retirement (46-55)","Seniors (55+)")))) -> Gen Z (18-25)
A6: 5 | B6: Female | C6: 18-25 | D6: 1 | E6: Salaried | F6: 50K-1L | G6: 2 | H6: Nexon | I6: Petrol | J6: Automatic | K6: 10L-18L | L6: 2 | M6: City Commute | N6: Safety | O6: Ground Clearance | P6: Budget | Q6: 360 Camera | R6: Website | S6: Digital | T6: Festival | U6: Venkataramana Motors | V6: Not recorded | W6: Reputation | X6: Yes | Y6: Yes | AA6: Plastic quality | AB6: Fit & Finish | AC6: =IF(H6="Punch","Entry",IF(OR(H6="Nexon",H6="Curvv"),"Compact","Premium")) -> Compact | AD6: =IF(C6="18-25","Gen Z (18-25)",IF(C6="26-35","Young professionals (26-35)",IF(C6="36-45","Family builders (36-45)",IF(C6="46-55","Pre-retirement (46-55)","Seniors (55+)")))) -> Gen Z (18-25)
A7: 6 | B7: Male | C7: 26-35 | D7: 2 | E7: Salaried | F7: Above 2L | G7: 4 | H7: Sierra | I7: CNG | J7: Automatic | K7: Above 25L | L7: 4 | M7: Highway/Long Distance | N7: Safety | O7: Ground Clearance | P7: Budget | Q7: 360 Camera | R7: Word of Mouth | S7: Digital | T7: Festival | U7: Tejaswi Motors | V7: Hi-Tech | W7: Proximity | X7: No | Y7: Yes | AA7: Service response | AB7: Service Competence & Capacity | AC7: =IF(H7="Punch","Entry",IF(OR(H7="Nexon",H7="Curvv"),"Compact","Premium")) -> Premium | AD7: =IF(C7="18-25","Gen Z (18-25)",IF(C7="26-35","Young professionals (26-35)",IF(C7="36-45","Family builders (36-45)",IF(C7="46-55","Pre-retirement (46-55)","Seniors (55+)")))) -> Young professionals (26-35)
A8: 7 | B8: Male | C8: 36-45 | D8: 3 | E8: Homemaker | F8: Below 50K | G8: 1 | H8: Sierra | I8: Diesel | J8: Automatic | K8: Below 10L | L8: 1 | M8: Highway/Long Distance | N8: Safety | O8: Ground Clearance | P8: Budget | Q8: 360 Camera | R8: Word of Mouth | S8: Loan | T8: Festival | U8: Select Cars | V8: Moosapet | W8: Test Drive | X8: No | Y8: No | Z8: Brand Trust | AA8: Panel gaps | AB8: Fit & Finish | AC8: =IF(H8="Punch","Entry",IF(OR(H8="Nexon",H8="Curvv"),"Compact","Premium")) -> Premium | AD8: =IF(C8="18-25","Gen Z (18-25)",IF(C8="26-35","Young professionals (26-35)",IF(C8="36-45","Family builders (36-45)",IF(C8="46-55","Pre-retirement (46-55)","Seniors (55+)")))) -> Family builders (36-45)
A9: 8 | B9: Female | C9: 26-35 | D9: 2 | E9: Salaried | F9: Above 2L | G9: 4 | H9: Nexon | I9: Diesel | J9: Automatic | K9: Above 25L | L9: 4 | M9: City Commute | N9: Safety | O9: Ground Clearance | P9: Budget | Q9: Sunroof | R9: Website | S9: Loan | T9: Birthday | U9: Venkataramana Motors | V9: Not recorded | W9: Reputation | X9: Yes | Y9: Yes | AA9: Plastic quality | AB9: Fit & Finish | AC9: =IF(H9="Punch","Entry",IF(OR(H9="Nexon",H9="Curvv"),"Compact","Premium")) -> Compact | AD9: =IF(C9="18-25","Gen Z (18-25)",IF(C9="26-35","Young professionals (26-35)",IF(C9="36-45","Family builders (36-45)",IF(C9="46-55","Pre-retirement (46-55)","Seniors (55+)")))) -> Young professionals (26-35)
A10: 9 | B10: Male | C10: 26-35 | D10: 2 | E10: Salaried | F10: 1L-2L | G10: 3 | H10: Sierra | I10: Diesel | J10: Automatic | K10: 18L-25L | L10: 3 | M10: Highway/Long Distance | N10: Safety | O10: Ground Clearance | P10: Budget | Q10: Sunroof | R10: Word of Mouth | S10: Loan | T10: Festival | U10: Select Cars | V10: Moosapet | W10: Test Drive | X10: No | Y10: No | Z10: Brand Trust | AA10: Panel gaps | AB10: Fit & Finish | AC10: =IF(H10="Punch","Entry",IF(OR(H10="Nexon",H10="Curvv"),"Compact","Premium")) -> Premium | AD10: =IF(C10="18-25","Gen Z (18-25)",IF(C10="26-35","Young professionals (26-35)",IF(C10="36-45","Family builders (36-45)",IF(C10="46-55","Pre-retirement (46-55)","Seniors (55+)")))) -> Young professionals (26-35)
A11: 10 | B11: Male | C11: 36-45 | D11: 3 | E11: Business | F11: Above 2L | G11: 4 | H11: Safari | I11: Diesel | J11: Automatic | K11: Above 25L | L11: 4 | M11: Highway/Long Distance | N11: Safety | O11: Spaciousness | P11: Status | Q11: 360 Camera | R11: Website | S11: Loan | T11: Anniversary | U11: Select Cars | V11: Moosapet | W11: Test Drive | X11: No | Y11: No | Z11: Brand Trust | AA11: Panel gaps | AB11: Fit & Finish | AC11: =IF(H11="Punch","Entry",IF(OR(H11="Nexon",H11="Curvv"),"Compact","Premium")) -> Premium | AD11: =IF(C11="18-25","Gen Z (18-25)",IF(C11="26-35","Young professionals (26-35)",IF(C11="36-45","Family builders (36-45)",IF(C11="46-55","Pre-retirement (46-55)","Seniors (55+)")))) -> Family builders (36-45)
A12: 11 | B12: Female | C12: 26-35 | D12: 2 | E12: Salaried | F12: 1L-2L | G12: 3 | H12: Curvv | I12: CNG | J12: Automatic | K12: 18L-25L | L12: 3 | M12: City Commute | N12: Safety | O12: Styling | P12: Status | Q12: 360 Camera | R12: Website | S12: Loan | T12: Birthday | U12: Venkataramana Motors | V12: Not recorded | W12: Reputation | X12: No | Y12: Yes | AA12: Plastic quality | AB12: Fit & Finish | AC12: =IF(H12="Punch","Entry",IF(OR(H12="Nexon",H12="Curvv"),"Compact","Premium")) -> Compact | AD12: =IF(C12="18-25","Gen Z (18-25)",IF(C12="26-35","Young professionals (26-35)",IF(C12="36-45","Family builders (36-45)",IF(C12="46-55","Pre-retirement (46-55)","Seniors (55+)")))) -> Young professionals (26-35)
A13: 12 | B13: Female | C13: 26-35 | D13: 2 | E13: Salaried | F13: 50K-1L | G13: 2 | H13: Curvv | I13: EV | J13: Automatic | K13: 10L-18L | L13: 2 | M13: City Commute | N13: Safety | O13: Styling | P13: Tech | Q13: Acti.ev Tech | R13: Website | S13: Loan | T13: Festival | U13: Select Cars | V13: Moosapet | W13: Test Drive | X13: No | Y13: No | Z13: Brand Trust | AA13: Panel gaps | AB13: Fit & Finish | AC13: =IF(H13="Punch","Entry",IF(OR(H13="Nexon",H13="Curvv"),"Compact","Premium")) -> Compact | AD13: =IF(C13="18-25","Gen Z (18-25)",IF(C13="26-35","Young professionals (26-35)",IF(C13="36-45","Family builders (36-45)",IF(C13="46-55","Pre-retirement (46-55)","Seniors (55+)")))) -> Young professionals (26-35)
A14: 13 | B14: Male | C14: Above 55 | D14: 5 | E14: Business | F14: Above 2L | G14: 4 | H14: Safari | I14: Petrol | J14: Automatic | K14: Above 25L | L14: 4 | M14: Highway/Long Distance | N14: Safety | O14: Spaciousness | P14: Status | Q14: 360 Camera | R14: Website | S14: Loan | T14: Anniversary | U14: Tejaswi Motors | V14: Hi-Tech | W14: Proximity | X14: No | Y14: Yes | AA14: Software stability | AB14: Software Instability | AC14: =IF(H14="Punch","Entry",IF(OR(H14="Nexon",H14="Curvv"),"Compact","Premium")) -> Premium | AD14: =IF(C14="18-25","Gen Z (18-25)",IF(C14="26-35","Young professionals (26-35)",IF(C14="36-45","Family builders (36-45)",IF(C14="46-55","Pre-retirement (46-55)","Seniors (55+)")))) -> Seniors (55+)
A15: 14 | B15: Male | C15: 18-25 | D15: 1 | E15: Salaried | F15: 1L-2L | G15: 3 | H15: Nexon | I15: EV | J15: Automatic | K15: 18L-25L | L15: 3 | M15: City Commute | N15: Safety | O15: Styling | P15: Tech | Q15: Acti.ev Tech | R15: Website | S15: Loan | T15: Birthday | U15: Select Cars | V15: Moosapet | W15: Test Drive | X15: Yes | Y15: Yes | AA15: Panel gaps | AB15: Fit & Finish | AC15: =IF(H15="Punch","Entry",IF(OR(H15="Nexon",H15="Curvv"),"Compact","Premium")) -> Compact | AD15: =IF(C15="18-25","Gen Z (18-25)",IF(C15="26-35","Young professionals (26-35)",IF(C15="36-45","Family builders (36-45)",IF(C15="46-55","Pre-retirement (46-55)","Seniors (55+)")))) -> Gen Z (18-25)
A16: 15 | B16: Male | C16: 18-25 | D16: 1 | E16: Salaried | F16: 50K-1L | G16: 2 | H16: Sierra | I16: Diesel | J16: Automatic | K16: 10L-18L | L16: 2 | M16: Highway/Long Distance | N16: Safety | O16: Ground Clearance | P16: Budget | Q16: Sunroof | R16: Website | S16: Digital | T16: Festival | U16: Venkataramana Motors | V16: Not recorded | W16: Reputation | X16: No | Y16: Yes | AA16: Fit and finish | AB16: Fit & Finish | AC16: =IF(H16="Punch","Entry",IF(OR(H16="Nexon",H16="Curvv"),"Compact","Premium")) -> Premium | AD16: =IF(C16="18-25","Gen Z (18-25)",IF(C16="26-35","Young professionals (26-35)",IF(C16="36-45","Family builders (36-45)",IF(C16="46-55","Pre-retirement (46-55)","Seniors (55+)")))) -> Gen Z (18-25)
A17: 16 | B17: Male | C17: 36-45 | D17: 3 | E17: Homemaker | F17: 50K-1L | G17: 2 | H17: Harrier | I17: Diesel | J17: Automatic | K17: 10L-18L | L17: 2 | M17: Highway/Long Distance | N17: Safety | O17: Spaciousness | P17: Status | Q17: Ventilated Seats | R17: Word of Mouth | S17: Loan | T17: Anniversary | U17: Venkataramana Motors | V17: Not recorded | W17: Reputation | X17: No | Y17: Yes | AA17: Plastic quality | AB17: Fit & Finish | AC17: =IF(H17="Punch","Entry",IF(OR(H17="Nexon",H17="Curvv"),"Compact","Premium")) -> Premium | AD17: =IF(C17="18-25","Gen Z (18-25)",IF(C17="26-35","Young professionals (26-35)",IF(C17="36-45","Family builders (36-45)",IF(C17="46-55","Pre-retirement (46-55)","Seniors (55+)")))) -> Family builders (36-45)
A18: 17 | B18: Female | C18: 36-45 | D18: 3 | E18: Homemaker | F18: 1L-2L | G18: 3 | H18: Sierra | I18: EV | J18: Automatic | K18: 18L-25L | L18: 3 | M18: Highway/Long Distance | N18: Safety | O18: Styling | P18: Tech | Q18: Acti.ev Tech | R18: Word of Mouth | S18: Loan | T18: Festival | U18: Select Cars | V18: Moosapet | W18: Test Drive | X18: No | Y18: No | Z18: Brand Trust | AA18: Panel gaps | AB18: Fit & Finish | AC18: =IF(H18="Punch","Entry",IF(OR(H18="Nexon",H18="Curvv"),"Compact","Premium")) -> Premium | AD18: =IF(C18="18-25","Gen Z (18-25)",IF(C18="26-35","Young professionals (26-35)",IF(C18="36-45","Family builders (36-45)",IF(C18="46-55","Pre-retirement (46-55)","Seniors (55+)")))) -> Family builders (36-45)
A19: 18 | B19: Male | C19: 46-55 | D19: 4 | E19: Homemaker | F19: 50K-1L | G19: 2 | H19: Harrier | I19: CNG | J19: Automatic | K19: 10L-18L | L19: 2 | M19: Highway/Long Distance | N19: Safety | O19: Spaciousness | P19: Status | Q19: Ventilated Seats | R19: YouTube | S19: Cheque | T19: Anniversary | U19: Venkataramana Motors | V19: Not recorded | W19: Reputation | X19: No | Y19: Yes | AA19: Fit and finish | AB19: Fit & Finish | AC19: =IF(H19="Punch","Entry",IF(OR(H19="Nexon",H19="Curvv"),"Compact","Premium")) -> Premium | AD19: =IF(C19="18-25","Gen Z (18-25)",IF(C19="26-35","Young professionals (26-35)",IF(C19="36-45","Family builders (36-45)",IF(C19="46-55","Pre-retirement (46-55)","Seniors (55+)")))) -> Pre-retirement (46-55)
A20: 19 | B20: Male | C20: 36-45 | D20: 3 | E20: Business | F20: Above 2L | G20: 4 | H20: Safari | I20: Petrol | J20: Automatic | K20: Above 25L | L20: 4 | M20: Highway/Long Distance | N20: Safety | O20: Spaciousness | P20: Status | Q20: 360 Camera | R20: YouTube | S20: Loan | T20: Anniversary | U20: Venkataramana Motors | V20: Not recorded | W20: Reputation | X20: No | Y20: Yes | AA20: Plastic quality | AB20: Fit & Finish | AC20: =IF(H20="Punch","Entry",IF(OR(H20="Nexon",H20="Curvv"),"Compact","Premium")) -> Premium | AD20: =IF(C20="18-25","Gen Z (18-25)",IF(C20="26-35","Young professionals (26-35)",IF(C20="36-45","Family builders (36-45)",IF(C20="46-55","Pre-retirement (46-55)","Seniors (55+)")))) -> Family builders (36-45)
A21: 20 | B21: Female | C21: 18-25 | D21: 1 | E21: Salaried | F21: Below 50K | G21: 1 | H21: Punch | I21: Petrol | J21: Manual | K21: Below 10L | L21: 1 | M21: City Commute | N21: Safety | O21: Ground Clearance | P21: Budget | Q21: Sunroof | R21: Word of Mouth | S21: Digital | T21: Festival | U21: Tejaswi Motors | V21: Hi-Tech | W21: Proximity | X21: Yes | Y21: Yes | AA21: Software stability | AB21: Software Instability | AC21: =IF(H21="Punch","Entry",IF(OR(H21="Nexon",H21="Curvv"),"Compact","Premium")) -> Entry | AD21: =IF(C21="18-25","Gen Z (18-25)",IF(C21="26-35","Young professionals (26-35)",IF(C21="36-45","Family builders (36-45)",IF(C21="46-55","Pre-retirement (46-55)","Seniors (55+)")))) -> Gen Z (18-25)
A22: 21 | B22: Male | C22: 18-25 | D22: 1 | E22: Salaried | F22: 1L-2L | G22: 3 | H22: Curvv | I22: EV | J22: Automatic | K22: 18L-25L | L22: 3 | M22: City Commute | N22: Safety | O22: Styling | P22: Tech | Q22: Acti.ev Tech | R22: YouTube | S22: Digital | T22: Birthday | U22: Select Cars | V22: Moosapet | W22: Test Drive | X22: No | Y22: Yes | AA22: Parts availability | AB22: Service Competence & Capacity | AC22: =IF(H22="Punch","Entry",IF(OR(H22="Nexon",H22="Curvv"),"Compact","Premium")) -> Compact | AD22: =IF(C22="18-25","Gen Z (18-25)",IF(C22="26-35","Young professionals (26-35)",IF(C22="36-45","Family builders (36-45)",IF(C22="46-55","Pre-retirement (46-55)","Seniors (55+)")))) -> Gen Z (18-25)
A23: 22 | B23: Male | C23: 36-45 | D23: 3 | E23: Homemaker | F23: 1L-2L | G23: 3 | H23: Sierra | I23: CNG | J23: Automatic | K23: 18L-25L | L23: 3 | M23: Highway/Long Distance | N23: Safety | O23: Ground Clearance | P23: Budget | Q23: Sunroof | R23: Website | S23: Digital | T23: Festival | U23: Tejaswi Motors | V23: Hi-Tech | W23: Proximity | X23: No | Y23: Yes | AA23: Software stability | AB23: Software Instability | AC23: =IF(H23="Punch","Entry",IF(OR(H23="Nexon",H23="Curvv"),"Compact","Premium")) -> Premium | AD23: =IF(C23="18-25","Gen Z (18-25)",IF(C23="26-35","Young professionals (26-35)",IF(C23="36-45","Family builders (36-45)",IF(C23="46-55","Pre-retirement (46-55)","Seniors (55+)")))) -> Family builders (36-45)
A24: 23 | B24: Female | C24: 18-25 | D24: 1 | E24: Salaried | F24: Below 50K | G24: 1 | H24: Punch | I24: Diesel | J24: Automatic | K24: Below 10L | L24: 1 | M24: City Commute | N24: Safety | O24: Ground Clearance | P24: Budget | Q24: Sunroof | R24: Word of Mouth | S24: Loan | T24: Festival | U24: Venkataramana Motors | V24: Not recorded | W24: Reputation | X24: Yes | Y24: Yes | AA24: Plastic quality | AB24: Fit & Finish | AC24: =IF(H24="Punch","Entry",IF(OR(H24="Nexon",H24="Curvv"),"Compact","Premium")) -> Entry | AD24: =IF(C24="18-25","Gen Z (18-25)",IF(C24="26-35","Young professionals (26-35)",IF(C24="36-45","Family builders (36-45)",IF(C24="46-55","Pre-retirement (46-55)","Seniors (55+)")))) -> Gen Z (18-25)
A25: 24 | B25: Female | C25: 46-55 | D25: 4 | E25: Homemaker | F25: 1L-2L | G25: 3 | H25: Safari | I25: CNG | J25: Automatic | K25: 18L-25L | L25: 3 | M25: Highway/Long Distance | N25: Safety | O25: Spaciousness | P25: Status | Q25: 360 Camera | R25: YouTube | S25: Cheque | T25: Festival | U25: Venkataramana Motors | V25: Not recorded | W25: Reputation | X25: No | Y25: Yes | AA25: Fit and finish | AB25: Fit & Finish | AC25: =IF(H25="Punch","Entry",IF(OR(H25="Nexon",H25="Curvv"),"Compact","Premium")) -> Premium | AD25: =IF(C25="18-25","Gen Z (18-25)",IF(C25="26-35","Young professionals (26-35)",IF(C25="36-45","Family builders (36-45)",IF(C25="46-55","Pre-retirement (46-55)","Seniors (55+)")))) -> Pre-retirement (46-55)
A26: 25 | B26: Female | C26: 36-45 | D26: 3 | E26: Homemaker | F26: 1L-2L | G26: 3 | H26: Safari | I26: Diesel | J26: Automatic | K26: 18L-25L | L26: 3 | M26: Highway/Long Distance | N26: Safety | O26: Spaciousness | P26: Status | Q26: 360 Camera | R26: Word of Mouth | S26: Digital | T26: Anniversary | U26: Select Cars | V26: Moosapet | W26: Test Drive | X26: No | Y26: Yes | AA26: Parts availability | AB26: Service Competence & Capacity | AC26: =IF(H26="Punch","Entry",IF(OR(H26="Nexon",H26="Curvv"),"Compact","Premium")) -> Premium | AD26: =IF(C26="18-25","Gen Z (18-25)",IF(C26="26-35","Young professionals (26-35)",IF(C26="36-45","Family builders (36-45)",IF(C26="46-55","Pre-retirement (46-55)","Seniors (55+)")))) -> Family builders (36-45)
A27: 26 | B27: Male | C27: 46-55 | D27: 4 | E27: Homemaker | F27: 1L-2L | G27: 3 | H27: Curvv | I27: Diesel | J27: Automatic | K27: 18L-25L | L27: 3 | M27: City Commute | N27: Safety | O27: Styling | P27: Status | Q27: 360 Camera | R27: Website | S27: Loan | T27: Anniversary | U27: Venkataramana Motors | V27: Not recorded | W27: Reputation | X27: No | Y27: Yes | AA27: Plastic quality | AB27: Fit & Finish | AC27: =IF(H27="Punch","Entry",IF(OR(H27="Nexon",H27="Curvv"),"Compact","Premium")) -> Compact | AD27: =IF(C27="18-25","Gen Z (18-25)",IF(C27="26-35","Young professionals (26-35)",IF(C27="36-45","Family builders (36-45)",IF(C27="46-55","Pre-retirement (46-55)","Seniors (55+)")))) -> Pre-retirement (46-55)
A28: 27 | B28: Male | C28: Above 55 | D28: 5 | E28: Business | F28: Above 2L | G28: 4 | H28: Safari | I28: EV | J28: Manual | K28: Above 25L | L28: 4 | M28: Highway/Long Distance | N28: Safety | O28: Styling | P28: Tech | Q28: Acti.ev Tech | R28: Word of Mouth | S28: Loan | T28: Festival | U28: Select Cars | V28: Moosapet | W28: Test Drive | X28: No | Y28: Yes | AA28: Panel gaps | AB28: Fit & Finish | AC28: =IF(H28="Punch","Entry",IF(OR(H28="Nexon",H28="Curvv"),"Compact","Premium")) -> Premium | AD28: =IF(C28="18-25","Gen Z (18-25)",IF(C28="26-35","Young professionals (26-35)",IF(C28="36-45","Family builders (36-45)",IF(C28="46-55","Pre-retirement (46-55)","Seniors (55+)")))) -> Seniors (55+)
A29: 28 | B29: Female | C29: 18-25 | D29: 1 | E29: Salaried | F29: Above 2L | G29: 4 | H29: Punch | I29: Petrol | J29: Automatic | K29: Above 25L | L29: 4 | M29: City Commute | N29: Safety | O29: Ground Clearance | P29: Budget | Q29: Sunroof | R29: YouTube | S29: Loan | T29: Festival | U29: Tejaswi Motors | V29: Hi-Tech | W29: Proximity | X29: Yes | Y29: Yes | AA29: Service response | AB29: Service Competence & Capacity | AC29: =IF(H29="Punch","Entry",IF(OR(H29="Nexon",H29="Curvv"),"Compact","Premium")) -> Entry | AD29: =IF(C29="18-25","Gen Z (18-25)",IF(C29="26-35","Young professionals (26-35)",IF(C29="36-45","Family builders (36-45)",IF(C29="46-55","Pre-retirement (46-55)","Seniors (55+)")))) -> Gen Z (18-25)
A30: 29 | B30: Male | C30: 36-45 | D30: 3 | E30: Homemaker | F30: 1L-2L | G30: 3 | H30: Safari | I30: EV | J30: Automatic | K30: 18L-25L | L30: 3 | M30: Highway/Long Distance | N30: Safety | O30: Styling | P30: Tech | Q30: Acti.ev Tech | R30: Word of Mouth | S30: Loan | T30: Anniversary | U30: Venkataramana Motors | V30: Not recorded | W30: Reputation | X30: No | Y30: Yes | AA30: Plastic quality | AB30: Fit & Finish | AC30: =IF(H30="Punch","Entry",IF(OR(H30="Nexon",H30="Curvv"),"Compact","Premium")) -> Premium | AD30: =IF(C30="18-25","Gen Z (18-25)",IF(C30="26-35","Young professionals (26-35)",IF(C30="36-45","Family builders (36-45)",IF(C30="46-55","Pre-retirement (46-55)","Seniors (55+)")))) -> Family builders (36-45)
A31: 30 | B31: Male | C31: Above 55 | D31: 5 | E31: Retired | F31: Below 50K | G31: 1 | H31: Curvv | I31: CNG | J31: Automatic | K31: Below 10L | L31: 1 | M31: City Commute | N31: Safety | O31: Styling | P31: Status | Q31: 360 Camera | R31: YouTube | S31: Cheque | T31: Anniversary | U31: Select Cars | V31: Moosapet | W31: Test Drive | X31: No | Y31: Yes | AA31: Panel gaps | AB31: Fit & Finish | AC31: =IF(H31="Punch","Entry",IF(OR(H31="Nexon",H31="Curvv"),"Compact","Premium")) -> Compact | AD31: =IF(C31="18-25","Gen Z (18-25)",IF(C31="26-35","Young professionals (26-35)",IF(C31="36-45","Family builders (36-45)",IF(C31="46-55","Pre-retirement (46-55)","Seniors (55+)")))) -> Seniors (55+)
A32: 31 | B32: Male | C32: 36-45 | D32: 3 | E32: Business | F32: Above 2L | G32: 4 | H32: Harrier | I32: Diesel | J32: Automatic | K32: Above 25L | L32: 4 | M32: Highway/Long Distance | N32: Safety | O32: Spaciousness | P32: Status | Q32: Ventilated Seats | R32: YouTube | S32: Loan | T32: Festival | U32: Select Cars | V32: Moosapet | W32: Test Drive | X32: No | Y32: No | Z32: Brand Trust | AA32: Parts availability | AB32: Service Competence & Capacity | AC32: =IF(H32="Punch","Entry",IF(OR(H32="Nexon",H32="Curvv"),"Compact","Premium")) -> Premium | AD32: =IF(C32="18-25","Gen Z (18-25)",IF(C32="26-35","Young professionals (26-35)",IF(C32="36-45","Family builders (36-45)",IF(C32="46-55","Pre-retirement (46-55)","Seniors (55+)")))) -> Family builders (36-45)
A33: 32 | B33: Male | C33: 18-25 | D33: 1 | E33: Salaried | F33: Below 50K | G33: 1 | H33: Nexon | I33: EV | J33: Automatic | K33: 18L-25L | L33: 3 | M33: City Commute | N33: Safety | O33: Styling | P33: Tech | Q33: Acti.ev Tech | R33: YouTube | S33: Digital | T33: Birthday | U33: Venkataramana Motors | V33: Not recorded | W33: Reputation | X33: Yes | Y33: Yes | AA33: Plastic quality | AB33: Fit & Finish | AC33: =IF(H33="Punch","Entry",IF(OR(H33="Nexon",H33="Curvv"),"Compact","Premium")) -> Compact | AD33: =IF(C33="18-25","Gen Z (18-25)",IF(C33="26-35","Young professionals (26-35)",IF(C33="36-45","Family builders (36-45)",IF(C33="46-55","Pre-retirement (46-55)","Seniors (55+)")))) -> Gen Z (18-25)
A34: 33 | B34: Male | C34: 46-55 | D34: 4 | E34: Homemaker | F34: 1L-2L | G34: 3 | H34: Nexon | I34: EV | J34: Manual | K34: 18L-25L | L34: 3 | M34: City Commute | N34: Safety | O34: Styling | P34: Tech | Q34: Acti.ev Tech | R34: YouTube | S34: Loan | T34: Anniversary | U34: Tejaswi Motors | V34: Hi-Tech | W34: Proximity | X34: Yes | Y34: Yes | AA34: Software stability | AB34: Software Instability | AC34: =IF(H34="Punch","Entry",IF(OR(H34="Nexon",H34="Curvv"),"Compact","Premium")) -> Compact | AD34: =IF(C34="18-25","Gen Z (18-25)",IF(C34="26-35","Young professionals (26-35)",IF(C34="36-45","Family builders (36-45)",IF(C34="46-55","Pre-retirement (46-55)","Seniors (55+)")))) -> Pre-retirement (46-55)
A35: 34 | B35: Male | C35: 18-25 | D35: 1 | E35: Salaried | F35: Above 2L | G35: 4 | H35: Sierra | I35: EV | J35: Automatic | K35: Above 25L | L35: 4 | M35: Highway/Long Distance | N35: Safety | O35: Styling | P35: Tech | Q35: Acti.ev Tech | R35: Website | S35: Digital | T35: Festival | U35: Venkataramana Motors | V35: Not recorded | W35: Reputation | X35: No | Y35: Yes | AA35: Plastic quality | AB35: Fit & Finish | AC35: =IF(H35="Punch","Entry",IF(OR(H35="Nexon",H35="Curvv"),"Compact","Premium")) -> Premium | AD35: =IF(C35="18-25","Gen Z (18-25)",IF(C35="26-35","Young professionals (26-35)",IF(C35="36-45","Family builders (36-45)",IF(C35="46-55","Pre-retirement (46-55)","Seniors (55+)")))) -> Gen Z (18-25)
A36: 35 | B36: Male | C36: 26-35 | D36: 2 | E36: Salaried | F36: Below 50K | G36: 1 | H36: Sierra | I36: EV | J36: Manual | K36: Below 10L | L36: 1 | M36: Highway/Long Distance | N36: Safety | O36: Styling | P36: Tech | Q36: Acti.ev Tech | R36: YouTube | S36: Loan | T36: Festival | U36: Venkataramana Motors | V36: Not recorded | W36: Reputation | X36: No | Y36: Yes | AA36: Plastic quality | AB36: Fit & Finish | AC36: =IF(H36="Punch","Entry",IF(OR(H36="Nexon",H36="Curvv"),"Compact","Premium")) -> Premium | AD36: =IF(C36="18-25","Gen Z (18-25)",IF(C36="26-35","Young professionals (26-35)",IF(C36="36-45","Family builders (36-45)",IF(C36="46-55","Pre-retirement (46-55)","Seniors (55+)")))) -> Young professionals (26-35)
A37: 36 | B37: Male | C37: 46-55 | D37: 4 | E37: Homemaker | F37: 1L-2L | G37: 3 | H37: Harrier | I37: CNG | J37: Automatic | K37: 18L-25L | L37: 3 | M37: Highway/Long Distance | N37: Safety | O37: Spaciousness | P37: Status | Q37: Ventilated Seats | R37: Website | S37: Loan | T37: Anniversary | U37: Venkataramana Motors | V37: Not recorded | W37: Reputation | X37: No | Y37: Yes | AA37: Plastic quality | AB37: Fit & Finish | AC37: =IF(H37="Punch","Entry",IF(OR(H37="Nexon",H37="Curvv"),"Compact","Premium")) -> Premium | AD37: =IF(C37="18-25","Gen Z (18-25)",IF(C37="26-35","Young professionals (26-35)",IF(C37="36-45","Family builders (36-45)",IF(C37="46-55","Pre-retirement (46-55)","Seniors (55+)")))) -> Pre-retirement (46-55)
A38: 37 | B38: Male | C38: 36-45 | D38: 3 | E38: Homemaker | F38: 1L-2L | G38: 3 | H38: Harrier | I38: Diesel | J38: Automatic | K38: 18L-25L | L38: 3 | M38: Highway/Long Distance | N38: Safety | O38: Spaciousness | P38: Status | Q38: Ventilated Seats | R38: YouTube | S38: Digital | T38: Festival | U38: Venkataramana Motors | V38: Not recorded | W38: Reputation | X38: No | Y38: Yes | AA38: Plastic quality | AB38: Fit & Finish | AC38: =IF(H38="Punch","Entry",IF(OR(H38="Nexon",H38="Curvv"),"Compact","Premium")) -> Premium | AD38: =IF(C38="18-25","Gen Z (18-25)",IF(C38="26-35","Young professionals (26-35)",IF(C38="36-45","Family builders (36-45)",IF(C38="46-55","Pre-retirement (46-55)","Seniors (55+)")))) -> Family builders (36-45)
A39: 38 | B39: Male | C39: 46-55 | D39: 4 | E39: Business | F39: Above 2L | G39: 4 | H39: Safari | I39: Diesel | J39: Automatic | K39: Above 25L | L39: 4 | M39: Highway/Long Distance | N39: Safety | O39: Spaciousness | P39: Status | Q39: Ventilated Seats | R39: YouTube | S39: Cheque | T39: Anniversary | U39: Select Cars | V39: Moosapet | W39: Test Drive | X39: No | Y39: Yes | AA39: Panel gaps | AB39: Fit & Finish | AC39: =IF(H39="Punch","Entry",IF(OR(H39="Nexon",H39="Curvv"),"Compact","Premium")) -> Premium | AD39: =IF(C39="18-25","Gen Z (18-25)",IF(C39="26-35","Young professionals (26-35)",IF(C39="36-45","Family builders (36-45)",IF(C39="46-55","Pre-retirement (46-55)","Seniors (55+)")))) -> Pre-retirement (46-55)
A40: 39 | B40: Male | C40: 36-45 | D40: 3 | E40: Homemaker | F40: Below 50K | G40: 1 | H40: Sierra | I40: Diesel | J40: Manual | K40: Below 10L | L40: 1 | M40: Highway/Long Distance | N40: Safety | O40: Ground Clearance | P40: Budget | Q40: 360 Camera | R40: Word of Mouth | S40: Loan | T40: Festival | U40: Tejaswi Motors | V40: Hi-Tech | W40: Proximity | X40: No | Y40: Yes | AA40: Infotainment lag | AB40: Software Instability | AC40: =IF(H40="Punch","Entry",IF(OR(H40="Nexon",H40="Curvv"),"Compact","Premium")) -> Premium | AD40: =IF(C40="18-25","Gen Z (18-25)",IF(C40="26-35","Young professionals (26-35)",IF(C40="36-45","Family builders (36-45)",IF(C40="46-55","Pre-retirement (46-55)","Seniors (55+)")))) -> Family builders (36-45)
A41: 40 | B41: Female | C41: 36-45 | D41: 3 | E41: Homemaker | F41: 1L-2L | G41: 3 | H41: Punch | I41: Petrol | J41: Manual | K41: 18L-25L | L41: 3 | M41: City Commute | N41: Safety | O41: Ground Clearance | P41: Budget | Q41: Sunroof | R41: Website | S41: Loan | T41: Festival | U41: Venkataramana Motors | V41: Not recorded | W41: Reputation | X41: Yes | Y41: Yes | AA41: Fit and finish | AB41: Fit & Finish | AC41: =IF(H41="Punch","Entry",IF(OR(H41="Nexon",H41="Curvv"),"Compact","Premium")) -> Entry | AD41: =IF(C41="18-25","Gen Z (18-25)",IF(C41="26-35","Young professionals (26-35)",IF(C41="36-45","Family builders (36-45)",IF(C41="46-55","Pre-retirement (46-55)","Seniors (55+)")))) -> Family builders (36-45)
A42: 41 | B42: Male | C42: 26-35 | D42: 2 | E42: Salaried | F42: 1L-2L | G42: 3 | H42: Curvv | I42: Petrol | J42: Automatic | K42: 18L-25L | L42: 3 | M42: City Commute | N42: Safety | O42: Styling | P42: Status | Q42: 360 Camera | R42: Website | S42: Digital | T42: Birthday | U42: Tejaswi Motors | V42: Hi-Tech | W42: Proximity | X42: No | Y42: Yes | AA42: Service response | AB42: Service Competence & Capacity | AC42: =IF(H42="Punch","Entry",IF(OR(H42="Nexon",H42="Curvv"),"Compact","Premium")) -> Compact | AD42: =IF(C42="18-25","Gen Z (18-25)",IF(C42="26-35","Young professionals (26-35)",IF(C42="36-45","Family builders (36-45)",IF(C42="46-55","Pre-retirement (46-55)","Seniors (55+)")))) -> Young professionals (26-35)
A43: 42 | B43: Male | C43: 46-55 | D43: 4 | E43: Business | F43: Above 2L | G43: 4 | H43: Safari | I43: Diesel | J43: Automatic | K43: Above 25L | L43: 4 | M43: Highway/Long Distance | N43: Safety | O43: Spaciousness | P43: Status | Q43: 360 Camera | R43: Website | S43: Loan | T43: Anniversary | U43: Select Cars | V43: Moosapet | W43: Test Drive | X43: No | Y43: Yes | AA43: Panel gaps | AB43: Fit & Finish | AC43: =IF(H43="Punch","Entry",IF(OR(H43="Nexon",H43="Curvv"),"Compact","Premium")) -> Premium | AD43: =IF(C43="18-25","Gen Z (18-25)",IF(C43="26-35","Young professionals (26-35)",IF(C43="36-45","Family builders (36-45)",IF(C43="46-55","Pre-retirement (46-55)","Seniors (55+)")))) -> Pre-retirement (46-55)
A44: 43 | B44: Female | C44: 36-45 | D44: 3 | E44: Business | F44: Above 2L | G44: 4 | H44: Safari | I44: EV | J44: Automatic | K44: Above 25L | L44: 4 | M44: Highway/Long Distance | N44: Safety | O44: Styling | P44: Tech | Q44: Acti.ev Tech | R44: Word of Mouth | S44: Loan | T44: Anniversary | U44: Tejaswi Motors | V44: Hi-Tech | W44: Proximity | X44: No | Y44: Yes | AA44: Service response | AB44: Service Competence & Capacity | AC44: =IF(H44="Punch","Entry",IF(OR(H44="Nexon",H44="Curvv"),"Compact","Premium")) -> Premium | AD44: =IF(C44="18-25","Gen Z (18-25)",IF(C44="26-35","Young professionals (26-35)",IF(C44="36-45","Family builders (36-45)",IF(C44="46-55","Pre-retirement (46-55)","Seniors (55+)")))) -> Family builders (36-45)
... A46: 45 | B46: Male | C46: 36-45 | D46: 3 | E46: Homemaker | F46: Below 50K | G46: 1 | H46: Harrier | I46: Diesel | J46: Automatic | K46: Below 10L | L46: 1 | M46: Highway/Long Distance | N46: Safety | O46: Spaciousness | P46: Status | Q46: 360 Camera | R46: Website | S46: Digital | T46: Festival | U46: Venkataramana Motors | V46: Not recorded | W46: Reputation | X46: No | Y46: Yes | AA46: Fit and finish | AB46: Fit & Finish | AC46: =IF(H46="Punch","Entry",IF(OR(H46="Nexon",H46="Curvv"),"Compact","Premium")) -> Premium | AD46: =IF(C46="18-25","Gen Z (18-25)",IF(C46="26-35","Young professionals (26-35)",IF(C46="36-45","Family builders (36-45)",IF(C46="46-55","Pre-retirement (46-55)","Seniors (55+)")))) -> Family builders (36-45)
A47: 46 | B47: Female | C47: 36-45 | D47: 3 | E47: Homemaker | F47: Below 50K | G47: 1 | H47: Punch | I47: Petrol | J47: Manual | K47: Below 10L | L47: 1 | M47: City Commute | N47: Safety | O47: Ground Clearance | P47: Budget | Q47: Sunroof | R47: YouTube | S47: Loan | T47: Festival | U47: Select Cars | V47: Moosapet | W47: Test Drive | X47: Yes | Y47: No | Z47: Brand Trust | AA47: Parts availability | AB47: Service Competence & Capacity | AC47: =IF(H47="Punch","Entry",IF(OR(H47="Nexon",H47="Curvv"),"Compact","Premium")) -> Entry | AD47: =IF(C47="18-25","Gen Z (18-25)",IF(C47="26-35","Young professionals (26-35)",IF(C47="36-45","Family builders (36-45)",IF(C47="46-55","Pre-retirement (46-55)","Seniors (55+)")))) -> Family builders (36-45)
A48: 47 | B48: Male | C48: 26-35 | D48: 2 | E48: Salaried | F48: 1L-2L | G48: 3 | H48: Nexon | I48: Diesel | J48: Manual | K48: 18L-25L | L48: 3 | M48: City Commute | N48: Safety | O48: Ground Clearance | P48: Budget | Q48: 360 Camera | R48: YouTube | S48: Loan | T48: Festival | U48: Select Cars | V48: Moosapet | W48: Test Drive | X48: Yes | Y48: Yes | AA48: Parts availability | AB48: Service Competence & Capacity | AC48: =IF(H48="Punch","Entry",IF(OR(H48="Nexon",H48="Curvv"),"Compact","Premium")) -> Compact | AD48: =IF(C48="18-25","Gen Z (18-25)",IF(C48="26-35","Young professionals (26-35)",IF(C48="36-45","Family builders (36-45)",IF(C48="46-55","Pre-retirement (46-55)","Seniors (55+)")))) -> Young professionals (26-35)
A49: 48 | B49: Male | C49: 46-55 | D49: 4 | E49: Homemaker | F49: Below 50K | G49: 1 | H49: Harrier | I49: Diesel | J49: Automatic | K49: Below 10L | L49: 1 | M49: Highway/Long Distance | N49: Safety | O49: Spaciousness | P49: Status | Q49: 360 Camera | R49: Website | S49: Loan | T49: Anniversary | U49: Tejaswi Motors | V49: Hi-Tech | W49: Proximity | X49: No | Y49: Yes | AA49: Service response | AB49: Service Competence & Capacity | AC49: =IF(H49="Punch","Entry",IF(OR(H49="Nexon",H49="Curvv"),"Compact","Premium")) -> Premium | AD49: =IF(C49="18-25","Gen Z (18-25)",IF(C49="26-35","Young professionals (26-35)",IF(C49="36-45","Family builders (36-45)",IF(C49="46-55","Pre-retirement (46-55)","Seniors (55+)")))) -> Pre-retirement (46-55)
A50: 49 | B50: Male | C50: 46-55 | D50: 4 | E50: Business | F50: Above 2L | G50: 4 | H50: Harrier | I50: Diesel | J50: Automatic | K50: Above 25L | L50: 4 | M50: Highway/Long Distance | N50: Safety | O50: Spaciousness | P50: Status | Q50: 360 Camera | R50: YouTube | S50: Loan | T50: Anniversary | U50: Tejaswi Motors | V50: Hi-Tech | W50: Proximity | X50: No | Y50: Yes | AA50: Software stability | AB50: Software Instability | AC50: =IF(H50="Punch","Entry",IF(OR(H50="Nexon",H50="Curvv"),"Compact","Premium")) -> Premium | AD50: =IF(C50="18-25","Gen Z (18-25)",IF(C50="26-35","Young professionals (26-35)",IF(C50="36-45","Family builders (36-45)",IF(C50="46-55","Pre-retirement (46-55)","Seniors (55+)")))) -> Pre-retirement (46-55)
A51: 50 | B51: Female | C51: 18-25 | D51: 1 | E51: Salaried | F51: 1L-2L | G51: 3 | H51: Punch | I51: EV | J51: Manual | K51: 10L-18L | L51: 2 | M51: City Commute | N51: Safety | O51: Styling | P51: Tech | Q51: Acti.ev Tech | R51: Word of Mouth | S51: Digital | T51: Birthday | U51: Select Cars | V51: Moosapet | W51: Test Drive | X51: Yes | Y51: Yes | AA51: Parts availability | AB51: Service Competence & Capacity | AC51: =IF(H51="Punch","Entry",IF(OR(H51="Nexon",H51="Curvv"),"Compact","Premium")) -> Entry | AD51: =IF(C51="18-25","Gen Z (18-25)",IF(C51="26-35","Young professionals (26-35)",IF(C51="36-45","Family builders (36-45)",IF(C51="46-55","Pre-retirement (46-55)","Seniors (55+)")))) -> Gen Z (18-25)
A52: 51 | B52: Female | C52: 18-25 | D52: 1 | E52: Salaried | F52: 50K-1L | G52: 2 | H52: Punch | I52: CNG | J52: Manual | K52: 10L-18L | L52: 2 | M52: City Commute | N52: Safety | O52: Ground Clearance | P52: Budget | Q52: Sunroof | R52: Word of Mouth | S52: Loan | T52: Festival | U52: Select Cars | V52: Moosapet | W52: Test Drive | X52: Yes | Y52: Yes | AA52: Panel gaps | AB52: Fit & Finish | AC52: =IF(H52="Punch","Entry",IF(OR(H52="Nexon",H52="Curvv"),"Compact","Premium")) -> Entry | AD52: =IF(C52="18-25","Gen Z (18-25)",IF(C52="26-35","Young professionals (26-35)",IF(C52="36-45","Family builders (36-45)",IF(C52="46-55","Pre-retirement (46-55)","Seniors (55+)")))) -> Gen Z (18-25)
A53: 52 | B53: Female | C53: 18-25 | D53: 1 | E53: Salaried | F53: Below 50K | G53: 1 | H53: Punch | I53: CNG | J53: Manual | K53: Below 10L | L53: 1 | M53: City Commute | N53: Safety | O53: Ground Clearance | P53: Budget | Q53: 360 Camera | R53: Word of Mouth | S53: Loan | T53: Birthday | U53: Venkataramana Motors | V53: Not recorded | W53: Reputation | X53: Yes | Y53: Yes | AA53: Plastic quality | AB53: Fit & Finish | AC53: =IF(H53="Punch","Entry",IF(OR(H53="Nexon",H53="Curvv"),"Compact","Premium")) -> Entry | AD53: =IF(C53="18-25","Gen Z (18-25)",IF(C53="26-35","Young professionals (26-35)",IF(C53="36-45","Family builders (36-45)",IF(C53="46-55","Pre-retirement (46-55)","Seniors (55+)")))) -> Gen Z (18-25)
A54: 53 | B54: Male | C54: 26-35 | D54: 2 | E54: Salaried | F54: 1L-2L | G54: 3 | H54: Curvv | I54: EV | J54: Automatic | K54: 18L-25L | L54: 3 | M54: City Commute | N54: Safety | O54: Styling | P54: Tech | Q54: Acti.ev Tech | R54: YouTube | S54: Digital | T54: Festival | U54: Tejaswi Motors | V54: Hi-Tech | W54: Proximity | X54: No | Y54: Yes | AA54: Software stability | AB54: Software Instability | AC54: =IF(H54="Punch","Entry",IF(OR(H54="Nexon",H54="Curvv"),"Compact","Premium")) -> Compact | AD54: =IF(C54="18-25","Gen Z (18-25)",IF(C54="26-35","Young professionals (26-35)",IF(C54="36-45","Family builders (36-45)",IF(C54="46-55","Pre-retirement (46-55)","Seniors (55+)")))) -> Young professionals (26-35)
A55: 54 | B55: Male | C55: 26-35 | D55: 2 | E55: Salaried | F55: 1L-2L | G55: 3 | H55: Nexon | I55: EV | J55: Manual | K55: 18L-25L | L55: 3 | M55: City Commute | N55: Safety | O55: Styling | P55: Tech | Q55: Acti.ev Tech | R55: Website | S55: Digital | T55: Festival | U55: Select Cars | V55: Moosapet | W55: Test Drive | X55: Yes | Y55: No | Z55: Brand Trust | AA55: Parts availability | AB55: Service Competence & Capacity | AC55: =IF(H55="Punch","Entry",IF(OR(H55="Nexon",H55="Curvv"),"Compact","Premium")) -> Compact | AD55: =IF(C55="18-25","Gen Z (18-25)",IF(C55="26-35","Young professionals (26-35)",IF(C55="36-45","Family builders (36-45)",IF(C55="46-55","Pre-retirement (46-55)","Seniors (55+)")))) -> Young professionals (26-35)
A56: 55 | B56: Female | C56: 36-45 | D56: 3 | E56: Homemaker | F56: 1L-2L | G56: 3 | H56: Safari | I56: Diesel | J56: Automatic | K56: 18L-25L | L56: 3 | M56: Highway/Long Distance | N56: Safety | O56: Spaciousness | P56: Status | Q56: Ventilated Seats | R56: Word of Mouth | S56: Digital | T56: Anniversary | U56: Venkataramana Motors | V56: Not recorded | W56: Reputation | X56: No | Y56: Yes | AA56: Fit and finish | AB56: Fit & Finish | AC56: =IF(H56="Punch","Entry",IF(OR(H56="Nexon",H56="Curvv"),"Compact","Premium")) -> Premium | AD56: =IF(C56="18-25","Gen Z (18-25)",IF(C56="26-35","Young professionals (26-35)",IF(C56="36-45","Family builders (36-45)",IF(C56="46-55","Pre-retirement (46-55)","Seniors (55+)")))) -> Family builders (36-45)
A57: 56 | B57: Male | C57: 18-25 | D57: 1 | E57: Salaried | F57: Above 2L | G57: 4 | H57: Nexon | I57: Petrol | J57: Manual | K57: Above 25L | L57: 4 | M57: City Commute | N57: Safety | O57: Ground Clearance | P57: Budget | Q57: 360 Camera | R57: Website | S57: Digital | T57: Festival | U57: Venkataramana Motors | V57: Not recorded | W57: Reputation | X57: Yes | Y57: Yes | AA57: Plastic quality | AB57: Fit & Finish | AC57: =IF(H57="Punch","Entry",IF(OR(H57="Nexon",H57="Curvv"),"Compact","Premium")) -> Compact | AD57: =IF(C57="18-25","Gen Z (18-25)",IF(C57="26-35","Young professionals (26-35)",IF(C57="36-45","Family builders (36-45)",IF(C57="46-55","Pre-retirement (46-55)","Seniors (55+)")))) -> Gen Z (18-25)
A58: 57 | B58: Female | C58: 46-55 | D58: 4 | E58: Homemaker | F58: Below 50K | G58: 1 | H58: Safari | I58: Diesel | J58: Automatic | K58: Below 10L | L58: 1 | M58: Highway/Long Distance | N58: Safety | O58: Spaciousness | P58: Status | Q58: 360 Camera | R58: Website | S58: Cheque | T58: Festival | U58: Venkataramana Motors | V58: Not recorded | W58: Reputation | X58: No | Y58: Yes | AA58: Fit and finish | AB58: Fit & Finish | AC58: =IF(H58="Punch","Entry",IF(OR(H58="Nexon",H58="Curvv"),"Compact","Premium")) -> Premium | AD58: =IF(C58="18-25","Gen Z (18-25)",IF(C58="26-35","Young professionals (26-35)",IF(C58="36-45","Family builders (36-45)",IF(C58="46-55","Pre-retirement (46-55)","Seniors (55+)")))) -> Pre-retirement (46-55)
A59: 58 | B59: Male | C59: 46-55 | D59: 4 | E59: Homemaker | F59: Below 50K | G59: 1 | H59: Safari | I59: Diesel | J59: Manual | K59: Below 10L | L59: 1 | M59: Highway/Long Distance | N59: Safety | O59: Spaciousness | P59: Status | Q59: Ventilated Seats | R59: Website | S59: Loan | T59: Festival | U59: Venkataramana Motors | V59: Not recorded | W59: Reputation | X59: No | Y59: Yes | AA59: Plastic quality | AB59: Fit & Finish | AC59: =IF(H59="Punch","Entry",IF(OR(H59="Nexon",H59="Curvv"),"Compact","Premium")) -> Premium | AD59: =IF(C59="18-25","Gen Z (18-25)",IF(C59="26-35","Young professionals (26-35)",IF(C59="36-45","Family builders (36-45)",IF(C59="46-55","Pre-retirement (46-55)","Seniors (55+)")))) -> Pre-retirement (46-55)
A60: 59 | B60: Male | C60: 18-25 | D60: 1 | E60: Salaried | F60: 50K-1L | G60: 2 | H60: Curvv | I60: CNG | J60: Automatic | K60: 10L-18L | L60: 2 | M60: City Commute | N60: Safety | O60: Styling | P60: Status | Q60: 360 Camera | R60: Word of Mouth | S60: Loan | T60: Birthday | U60: Tejaswi Motors | V60: Hi-Tech | W60: Proximity | X60: No | Y60: Yes | AA60: Service response | AB60: Service Competence & Capacity | AC60: =IF(H60="Punch","Entry",IF(OR(H60="Nexon",H60="Curvv"),"Compact","Premium")) -> Compact | AD60: =IF(C60="18-25","Gen Z (18-25)",IF(C60="26-35","Young professionals (26-35)",IF(C60="36-45","Family builders (36-45)",IF(C60="46-55","Pre-retirement (46-55)","Seniors (55+)")))) -> Gen Z (18-25)
A61: 60 | B61: Female | C61: Above 55 | D61: 5 | E61: Retired | F61: 1L-2L | G61: 3 | H61: Punch | I61: Petrol | J61: Manual | K61: 18L-25L | L61: 3 | M61: City Commute | N61: Safety | O61: Ground Clearance | P61: Budget | Q61: Sunroof | R61: YouTube | S61: Loan | T61: Anniversary | U61: Select Cars | V61: Moosapet | W61: Test Drive | X61: Yes | Y61: No | Z61: Brand Trust | AA61: Parts availability | AB61: Service Competence & Capacity | AC61: =IF(H61="Punch","Entry",IF(OR(H61="Nexon",H61="Curvv"),"Compact","Premium")) -> Entry | AD61: =IF(C61="18-25","Gen Z (18-25)",IF(C61="26-35","Young professionals (26-35)",IF(C61="36-45","Family builders (36-45)",IF(C61="46-55","Pre-retirement (46-55)","Seniors (55+)")))) -> Seniors (55+)
A62: 61 | B62: Male | C62: 18-25 | D62: 1 | E62: Salaried | F62: 50K-1L | G62: 2 | H62: Nexon | I62: Petrol | J62: Manual | K62: 10L-18L | L62: 2 | M62: City Commute | N62: Safety | O62: Ground Clearance | P62: Budget | Q62: Sunroof | R62: YouTube | S62: Loan | T62: Festival | U62: Select Cars | V62: Moosapet | W62: Test Drive | X62: Yes | Y62: No | Z62: Brand Trust | AA62: Parts availability | AB62: Service Competence & Capacity | AC62: =IF(H62="Punch","Entry",IF(OR(H62="Nexon",H62="Curvv"),"Compact","Premium")) -> Compact | AD62: =IF(C62="18-25","Gen Z (18-25)",IF(C62="26-35","Young professionals (26-35)",IF(C62="36-45","Family builders (36-45)",IF(C62="46-55","Pre-retirement (46-55)","Seniors (55+)")))) -> Gen Z (18-25)
A63: 62 | B63: Male | C63: 18-25 | D63: 1 | E63: Salaried | F63: Below 50K | G63: 1 | H63: Nexon | I63: EV | J63: Manual | K63: 18L-25L | L63: 3 | M63: City Commute | N63: Safety | O63: Styling | P63: Tech | Q63: Acti.ev Tech | R63: Website | S63: Loan | T63: Birthday | U63: Tejaswi Motors | V63: Hi-Tech | W63: Proximity | X63: Yes | Y63: Yes | AA63: Service response | AB63: Service Competence & Capacity | AC63: =IF(H63="Punch","Entry",IF(OR(H63="Nexon",H63="Curvv"),"Compact","Premium")) -> Compact | AD63: =IF(C63="18-25","Gen Z (18-25)",IF(C63="26-35","Young professionals (26-35)",IF(C63="36-45","Family builders (36-45)",IF(C63="46-55","Pre-retirement (46-55)","Seniors (55+)")))) -> Gen Z (18-25)
A64: 63 | B64: Female | C64: Above 55 | D64: 5 | E64: Retired | F64: Below 50K | G64: 1 | H64: Punch | I64: Diesel | J64: Manual | K64: Below 10L | L64: 1 | M64: City Commute | N64: Safety | O64: Ground Clearance | P64: Budget | Q64: 360 Camera | R64: Website | S64: Loan | T64: Anniversary | U64: Tejaswi Motors | V64: Hi-Tech | W64: Proximity | X64: Yes | Y64: Yes | AA64: Service response | AB64: Service Competence & Capacity | AC64: =IF(H64="Punch","Entry",IF(OR(H64="Nexon",H64="Curvv"),"Compact","Premium")) -> Entry | AD64: =IF(C64="18-25","Gen Z (18-25)",IF(C64="26-35","Young professionals (26-35)",IF(C64="36-45","Family builders (36-45)",IF(C64="46-55","Pre-retirement (46-55)","Seniors (55+)")))) -> Seniors (55+)
A65: 64 | B65: Male | C65: 26-35 | D65: 2 | E65: Salaried | F65: Above 2L | G65: 4 | H65: Sierra | I65: EV | J65: Automatic | K65: Above 25L | L65: 4 | M65: Highway/Long Distance | N65: Safety | O65: Styling | P65: Tech | Q65: Acti.ev Tech | R65: Website | S65: Loan | T65: Birthday | U65: Select Cars | V65: Moosapet | W65: Test Drive | X65: No | Y65: No | Z65: Brand Trust | AA65: Panel gaps | AB65: Fit & Finish | AC65: =IF(H65="Punch","Entry",IF(OR(H65="Nexon",H65="Curvv"),"Compact","Premium")) -> Premium | AD65: =IF(C65="18-25","Gen Z (18-25)",IF(C65="26-35","Young professionals (26-35)",IF(C65="36-45","Family builders (36-45)",IF(C65="46-55","Pre-retirement (46-55)","Seniors (55+)")))) -> Young professionals (26-35)
A66: 65 | B66: Male | C66: 46-55 | D66: 4 | E66: Business | F66: Above 2L | G66: 4 | H66: Harrier | I66: Petrol | J66: Automatic | K66: Above 25L | L66: 4 | M66: Highway/Long Distance | N66: Safety | O66: Spaciousness | P66: Status | Q66: Ventilated Seats | R66: Website | S66: Loan | T66: Festival | U66: Tejaswi Motors | V66: Hi-Tech | W66: Proximity | X66: No | Y66: Yes | AA66: Service response | AB66: Service Competence & Capacity | AC66: =IF(H66="Punch","Entry",IF(OR(H66="Nexon",H66="Curvv"),"Compact","Premium")) -> Premium | AD66: =IF(C66="18-25","Gen Z (18-25)",IF(C66="26-35","Young professionals (26-35)",IF(C66="36-45","Family builders (36-45)",IF(C66="46-55","Pre-retirement (46-55)","Seniors (55+)")))) -> Pre-retirement (46-55)
A67: 66 | B67: Male | C67: 46-55 | D67: 4 | E67: Homemaker | F67: 50K-1L | G67: 2 | H67: Curvv | I67: EV | J67: Automatic | K67: 10L-18L | L67: 2 | M67: City Commute | N67: Safety | O67: Styling | P67: Tech | Q67: Acti.ev Tech | R67: Website | S67: Loan | T67: Anniversary | U67: Select Cars | V67: Moosapet | W67: Test Drive | X67: No | Y67: No | Z67: Brand Trust | AA67: Panel gaps | AB67: Fit & Finish | AC67: =IF(H67="Punch","Entry",IF(OR(H67="Nexon",H67="Curvv"),"Compact","Premium")) -> Compact | AD67: =IF(C67="18-25","Gen Z (18-25)",IF(C67="26-35","Young professionals (26-35)",IF(C67="36-45","Family builders (36-45)",IF(C67="46-55","Pre-retirement (46-55)","Seniors (55+)")))) -> Pre-retirement (46-55)
A68: 67 | B68: Male | C68: 26-35 | D68: 2 | E68: Salaried | F68: 50K-1L | G68: 2 | H68: Curvv | I68: CNG | J68: Manual | K68: 10L-18L | L68: 2 | M68: City Commute | N68: Safety | O68: Styling | P68: Status | Q68: 360 Camera | R68: YouTube | S68: Loan | T68: Festival | U68: Tejaswi Motors | V68: Hi-Tech | W68: Proximity | X68: No | Y68: Yes | AA68: Software stability | AB68: Software Instability | AC68: =IF(H68="Punch","Entry",IF(OR(H68="Nexon",H68="Curvv"),"Compact","Premium")) -> Compact | AD68: =IF(C68="18-25","Gen Z (18-25)",IF(C68="26-35","Young professionals (26-35)",IF(C68="36-45","Family builders (36-45)",IF(C68="46-55","Pre-retirement (46-55)","Seniors (55+)")))) -> Young professionals (26-35)
A69: 68 | B69: Female | C69: 26-35 | D69: 2 | E69: Salaried | F69: 50K-1L | G69: 2 | H69: Nexon | I69: EV | J69: Automatic | K69: 18L-25L | L69: 3 | M69: City Commute | N69: Safety | O69: Styling | P69: Tech | Q69: Acti.ev Tech | R69: Website | S69: Loan | T69: Birthday | U69: Venkataramana Motors | V69: Not recorded | W69: Reputation | X69: Yes | Y69: Yes | AA69: Fit and finish | AB69: Fit & Finish | AC69: =IF(H69="Punch","Entry",IF(OR(H69="Nexon",H69="Curvv"),"Compact","Premium")) -> Compact | AD69: =IF(C69="18-25","Gen Z (18-25)",IF(C69="26-35","Young professionals (26-35)",IF(C69="36-45","Family builders (36-45)",IF(C69="46-55","Pre-retirement (46-55)","Seniors (55+)")))) -> Young professionals (26-35)
A70: 69 | B70: Female | C70: 18-25 | D70: 1 | E70: Salaried | F70: Above 2L | G70: 4 | H70: Punch | I70: Petrol | J70: Manual | K70: Above 25L | L70: 4 | M70: City Commute | N70: Safety | O70: Ground Clearance | P70: Budget | Q70: Sunroof | R70: Word of Mouth | S70: Loan | T70: Birthday | U70: Select Cars | V70: Moosapet | W70: Test Drive | X70: Yes | Y70: No | Z70: Brand Trust | AA70: Parts availability | AB70: Service Competence & Capacity | AC70: =IF(H70="Punch","Entry",IF(OR(H70="Nexon",H70="Curvv"),"Compact","Premium")) -> Entry | AD70: =IF(C70="18-25","Gen Z (18-25)",IF(C70="26-35","Young professionals (26-35)",IF(C70="36-45","Family builders (36-45)",IF(C70="46-55","Pre-retirement (46-55)","Seniors (55+)")))) -> Gen Z (18-25)
A71: 70 | B71: Male | C71: 26-35 | D71: 2 | E71: Salaried | F71: 50K-1L | G71: 2 | H71: Sierra | I71: Petrol | J71: Automatic | K71: 10L-18L | L71: 2 | M71: Highway/Long Distance | N71: Safety | O71: Ground Clearance | P71: Budget | Q71: Sunroof | R71: Word of Mouth | S71: Loan | T71: Festival | U71: Tejaswi Motors | V71: Hi-Tech | W71: Proximity | X71: No | Y71: Yes | AA71: Software stability | AB71: Software Instability | AC71: =IF(H71="Punch","Entry",IF(OR(H71="Nexon",H71="Curvv"),"Compact","Premium")) -> Premium | AD71: =IF(C71="18-25","Gen Z (18-25)",IF(C71="26-35","Young professionals (26-35)",IF(C71="36-45","Family builders (36-45)",IF(C71="46-55","Pre-retirement (46-55)","Seniors (55+)")))) -> Young professionals (26-35)
A72: 71 | B72: Male | C72: 36-45 | D72: 3 | E72: Homemaker | F72: 50K-1L | G72: 2 | H72: Punch | I72: CNG | J72: Manual | K72: 10L-18L | L72: 2 | M72: City Commute | N72: Safety | O72: Ground Clearance | P72: Budget | Q72: 360 Camera | R72: YouTube | S72: Loan | T72: Festival | U72: Venkataramana Motors | V72: Not recorded | W72: Reputation | X72: Yes | Y72: Yes | AA72: Plastic quality | AB72: Fit & Finish | AC72: =IF(H72="Punch","Entry",IF(OR(H72="Nexon",H72="Curvv"),"Compact","Premium")) -> Entry | AD72: =IF(C72="18-25","Gen Z (18-25)",IF(C72="26-35","Young professionals (26-35)",IF(C72="36-45","Family builders (36-45)",IF(C72="46-55","Pre-retirement (46-55)","Seniors (55+)")))) -> Family builders (36-45)
A73: 72 | B73: Male | C73: 26-35 | D73: 2 | E73: Salaried | F73: 1L-2L | G73: 3 | H73: Curvv | I73: Petrol | J73: Automatic | K73: 18L-25L | L73: 3 | M73: City Commute | N73: Safety | O73: Styling | P73: Status | Q73: 360 Camera | R73: Word of Mouth | S73: Loan | T73: Birthday | U73: Select Cars | V73: Moosapet | W73: Test Drive | X73: No | Y73: No | Z73: Brand Trust | AA73: Panel gaps | AB73: Fit & Finish | AC73: =IF(H73="Punch","Entry",IF(OR(H73="Nexon",H73="Curvv"),"Compact","Premium")) -> Compact | AD73: =IF(C73="18-25","Gen Z (18-25)",IF(C73="26-35","Young professionals (26-35)",IF(C73="36-45","Family builders (36-45)",IF(C73="46-55","Pre-retirement (46-55)","Seniors (55+)")))) -> Young professionals (26-35)
A74: 73 | B74: Male | C74: 18-25 | D74: 1 | E74: Salaried | F74: 50K-1L | G74: 2 | H74: Curvv | I74: Petrol | J74: Automatic | K74: 10L-18L | L74: 2 | M74: City Commute | N74: Safety | O74: Styling | P74: Status | Q74: 360 Camera | R74: Website | S74: Loan | T74: Festival | U74: Venkataramana Motors | V74: Not recorded | W74: Reputation | X74: No | Y74: Yes | AA74: Fit and finish | AB74: Fit & Finish | AC74: =IF(H74="Punch","Entry",IF(OR(H74="Nexon",H74="Curvv"),"Compact","Premium")) -> Compact | AD74: =IF(C74="18-25","Gen Z (18-25)",IF(C74="26-35","Young professionals (26-35)",IF(C74="36-45","Family builders (36-45)",IF(C74="46-55","Pre-retirement (46-55)","Seniors (55+)")))) -> Gen Z (18-25)
A75: 74 | B75: Female | C75: Above 55 | D75: 5 | E75: Retired | F75: 50K-1L | G75: 2 | H75: Nexon | I75: EV | J75: Manual | K75: 18L-25L | L75: 3 | M75: City Commute | N75: Safety | O75: Styling | P75: Tech | Q75: Acti.ev Tech | R75: Website | S75: Loan | T75: Anniversary | U75: Venkataramana Motors | V75: Not recorded | W75: Reputation | X75: Yes | Y75: Yes | AA75: Fit and finish | AB75: Fit & Finish | AC75: =IF(H75="Punch","Entry",IF(OR(H75="Nexon",H75="Curvv"),"Compact","Premium")) -> Compact | AD75: =IF(C75="18-25","Gen Z (18-25)",IF(C75="26-35","Young professionals (26-35)",IF(C75="36-45","Family builders (36-45)",IF(C75="46-55","Pre-retirement (46-55)","Seniors (55+)")))) -> Seniors (55+)
A76: 75 | B76: Male | C76: 26-35 | D76: 2 | E76: Salaried | F76: Above 2L | G76: 4 | H76: Harrier | I76: EV | J76: Automatic | K76: Above 25L | L76: 4 | M76: Highway/Long Distance | N76: Safety | O76: Styling | P76: Tech | Q76: Acti.ev Tech | R76: Website | S76: Loan | T76: Birthday | U76: Select Cars | V76: Moosapet | W76: Test Drive | X76: No | Y76: Yes | AA76: Parts availability | AB76: Service Competence & Capacity | AC76: =IF(H76="Punch","Entry",IF(OR(H76="Nexon",H76="Curvv"),"Compact","Premium")) -> Premium | AD76: =IF(C76="18-25","Gen Z (18-25)",IF(C76="26-35","Young professionals (26-35)",IF(C76="36-45","Family builders (36-45)",IF(C76="46-55","Pre-retirement (46-55)","Seniors (55+)")))) -> Young professionals (26-35)
A77: 76 | B77: Male | C77: 26-35 | D77: 2 | E77: Salaried | F77: 1L-2L | G77: 3 | H77: Sierra | I77: Petrol | J77: Automatic | K77: 18L-25L | L77: 3 | M77: Highway/Long Distance | N77: Safety | O77: Ground Clearance | P77: Budget | Q77: Sunroof | R77: Word of Mouth | S77: Loan | T77: Festival | U77: Select Cars | V77: Moosapet | W77: Test Drive | X77: No | Y77: Yes | AA77: Panel gaps | AB77: Fit & Finish | AC77: =IF(H77="Punch","Entry",IF(OR(H77="Nexon",H77="Curvv"),"Compact","Premium")) -> Premium | AD77: =IF(C77="18-25","Gen Z (18-25)",IF(C77="26-35","Young professionals (26-35)",IF(C77="36-45","Family builders (36-45)",IF(C77="46-55","Pre-retirement (46-55)","Seniors (55+)")))) -> Young professionals (26-35)
A78: 77 | B78: Female | C78: 36-45 | D78: 3 | E78: Homemaker | F78: 1L-2L | G78: 3 | H78: Safari | I78: Diesel | J78: Automatic | K78: 18L-25L | L78: 3 | M78: Highway/Long Distance | N78: Safety | O78: Spaciousness | P78: Status | Q78: Ventilated Seats | R78: Word of Mouth | S78: Loan | T78: Festival | U78: Venkataramana Motors | V78: Not recorded | W78: Reputation | X78: No | Y78: Yes | AA78: Fit and finish | AB78: Fit & Finish | AC78: =IF(H78="Punch","Entry",IF(OR(H78="Nexon",H78="Curvv"),"Compact","Premium")) -> Premium | AD78: =IF(C78="18-25","Gen Z (18-25)",IF(C78="26-35","Young professionals (26-35)",IF(C78="36-45","Family builders (36-45)",IF(C78="46-55","Pre-retirement (46-55)","Seniors (55+)")))) -> Family builders (36-45)
A79: 78 | B79: Male | C79: 46-55 | D79: 4 | E79: Business | F79: Above 2L | G79: 4 | H79: Harrier | I79: Diesel | J79: Automatic | K79: Above 25L | L79: 4 | M79: Highway/Long Distance | N79: Safety | O79: Spaciousness | P79: Status | Q79: Ventilated Seats | R79: Website | S79: Loan | T79: Festival | U79: Select Cars | V79: Moosapet | W79: Test Drive | X79: No | Y79: No | Z79: Brand Trust | AA79: Panel gaps | AB79: Fit & Finish | AC79: =IF(H79="Punch","Entry",IF(OR(H79="Nexon",H79="Curvv"),"Compact","Premium")) -> Premium | AD79: =IF(C79="18-25","Gen Z (18-25)",IF(C79="26-35","Young professionals (26-35)",IF(C79="36-45","Family builders (36-45)",IF(C79="46-55","Pre-retirement (46-55)","Seniors (55+)")))) -> Pre-retirement (46-55)
A80: 79 | B80: Female | C80: 26-35 | D80: 2 | E80: Salaried | F80: Above 2L | G80: 4 | H80: Nexon | I80: EV | J80: Manual | K80: 18L-25L | L80: 3 | M80: City Commute | N80: Safety | O80: Styling | P80: Tech | Q80: Acti.ev Tech | R80: Word of Mouth | S80: Loan | T80: Birthday | U80: Venkataramana Motors | V80: Not recorded | W80: Reputation | X80: Yes | Y80: Yes | AA80: Plastic quality | AB80: Fit & Finish | AC80: =IF(H80="Punch","Entry",IF(OR(H80="Nexon",H80="Curvv"),"Compact","Premium")) -> Compact | AD80: =IF(C80="18-25","Gen Z (18-25)",IF(C80="26-35","Young professionals (26-35)",IF(C80="36-45","Family builders (36-45)",IF(C80="46-55","Pre-retirement (46-55)","Seniors (55+)")))) -> Young professionals (26-35)
A81: 80 | B81: Male | C81: 36-45 | D81: 3 | E81: Homemaker | F81: Below 50K | G81: 1 | H81: Safari | I81: Diesel | J81: Automatic | K81: Below 10L | L81: 1 | M81: Highway/Long Distance | N81: Safety | O81: Spaciousness | P81: Status | Q81: Ventilated Seats | R81: Word of Mouth | S81: Loan | T81: Anniversary | U81: Select Cars | V81: Moosapet | W81: Test Drive | X81: No | Y81: No | Z81: Brand Trust | AA81: Panel gaps | AB81: Fit & Finish | AC81: =IF(H81="Punch","Entry",IF(OR(H81="Nexon",H81="Curvv"),"Compact","Premium")) -> Premium | AD81: =IF(C81="18-25","Gen Z (18-25)",IF(C81="26-35","Young professionals (26-35)",IF(C81="36-45","Family builders (36-45)",IF(C81="46-55","Pre-retirement (46-55)","Seniors (55+)")))) -> Family builders (36-45)
A82: 81 | B82: Male | C82: 46-55 | D82: 4 | E82: Homemaker | F82: 1L-2L | G82: 3 | H82: Harrier | I82: Diesel | J82: Manual | K82: 18L-25L | L82: 3 | M82: Highway/Long Distance | N82: Safety | O82: Spaciousness | P82: Status | Q82: Ventilated Seats | R82: YouTube | S82: Cheque | T82: Anniversary | U82: Select Cars | V82: Moosapet | W82: Test Drive | X82: No | Y82: Yes | AA82: Parts availability | AB82: Service Competence & Capacity | AC82: =IF(H82="Punch","Entry",IF(OR(H82="Nexon",H82="Curvv"),"Compact","Premium")) -> Premium | AD82: =IF(C82="18-25","Gen Z (18-25)",IF(C82="26-35","Young professionals (26-35)",IF(C82="36-45","Family builders (36-45)",IF(C82="46-55","Pre-retirement (46-55)","Seniors (55+)")))) -> Pre-retirement (46-55)
A83: 82 | B83: Male | C83: 26-35 | D83: 2 | E83: Salaried | F83: 50K-1L | G83: 2 | H83: Sierra | I83: Diesel | J83: Manual | K83: 10L-18L | L83: 2 | M83: Highway/Long Distance | N83: Safety | O83: Ground Clearance | P83: Budget | Q83: 360 Camera | R83: Word of Mouth | S83: Loan | T83: Birthday | U83: Venkataramana Motors | V83: Not recorded | W83: Reputation | X83: No | Y83: Yes | AA83: Fit and finish | AB83: Fit & Finish | AC83: =IF(H83="Punch","Entry",IF(OR(H83="Nexon",H83="Curvv"),"Compact","Premium")) -> Premium | AD83: =IF(C83="18-25","Gen Z (18-25)",IF(C83="26-35","Young professionals (26-35)",IF(C83="36-45","Family builders (36-45)",IF(C83="46-55","Pre-retirement (46-55)","Seniors (55+)")))) -> Young professionals (26-35)
A84: 83 | B84: Male | C84: 36-45 | D84: 3 | E84: Business | F84: Above 2L | G84: 4 | H84: Safari | I84: Petrol | J84: Automatic | K84: Above 25L | L84: 4 | M84: Highway/Long Distance | N84: Safety | O84: Spaciousness | P84: Status | Q84: 360 Camera | R84: Website | S84: Loan | T84: Festival | U84: Tejaswi Motors | V84: Hi-Tech | W84: Proximity | X84: No | Y84: Yes | AA84: Service response | AB84: Service Competence & Capacity | AC84: =IF(H84="Punch","Entry",IF(OR(H84="Nexon",H84="Curvv"),"Compact","Premium")) -> Premium | AD84: =IF(C84="18-25","Gen Z (18-25)",IF(C84="26-35","Young professionals (26-35)",IF(C84="36-45","Family builders (36-45)",IF(C84="46-55","Pre-retirement (46-55)","Seniors (55+)")))) -> Family builders (36-45)
A85: 84 | B85: Female | C85: 18-25 | D85: 1 | E85: Salaried | F85: Above 2L | G85: 4 | H85: Punch | I85: CNG | J85: Manual | K85: Above 25L | L85: 4 | M85: City Commute | N85: Safety | O85: Ground Clearance | P85: Budget | Q85: Sunroof | R85: YouTube | S85: Loan | T85: Birthday | U85: Venkataramana Motors | V85: Not recorded | W85: Reputation | X85: Yes | Y85: Yes | AA85: Plastic quality | AB85: Fit & Finish | AC85: =IF(H85="Punch","Entry",IF(OR(H85="Nexon",H85="Curvv"),"Compact","Premium")) -> Entry | AD85: =IF(C85="18-25","Gen Z (18-25)",IF(C85="26-35","Young professionals (26-35)",IF(C85="36-45","Family builders (36-45)",IF(C85="46-55","Pre-retirement (46-55)","Seniors (55+)")))) -> Gen Z (18-25)
A86: 85 | B86: Male | C86: 46-55 | D86: 4 | E86: Business | F86: Above 2L | G86: 4 | H86: Nexon | I86: EV | J86: Automatic | K86: 18L-25L | L86: 3 | M86: City Commute | N86: Safety | O86: Styling | P86: Tech | Q86: Acti.ev Tech | R86: Word of Mouth | S86: Cheque | T86: Festival | U86: Select Cars | V86: Moosapet | W86: Test Drive | X86: Yes | Y86: Yes | AA86: Parts availability | AB86: Service Competence & Capacity | AC86: =IF(H86="Punch","Entry",IF(OR(H86="Nexon",H86="Curvv"),"Compact","Premium")) -> Compact | AD86: =IF(C86="18-25","Gen Z (18-25)",IF(C86="26-35","Young professionals (26-35)",IF(C86="36-45","Family builders (36-45)",IF(C86="46-55","Pre-retirement (46-55)","Seniors (55+)")))) -> Pre-retirement (46-55)
A87: 86 | B87: Male | C87: 26-35 | D87: 2 | E87: Salaried | F87: Above 2L | G87: 4 | H87: Sierra | I87: EV | J87: Automatic | K87: Above 25L | L87: 4 | M87: Highway/Long Distance | N87: Safety | O87: Styling | P87: Tech | Q87: Acti.ev Tech | R87: Word of Mouth | S87: Loan | T87: Birthday | U87: Select Cars | V87: Moosapet | W87: Test Drive | X87: No | Y87: No | Z87: Brand Trust | AA87: Panel gaps | AB87: Fit & Finish | AC87: =IF(H87="Punch","Entry",IF(OR(H87="Nexon",H87="Curvv"),"Compact","Premium")) -> Premium | AD87: =IF(C87="18-25","Gen Z (18-25)",IF(C87="26-35","Young professionals (26-35)",IF(C87="36-45","Family builders (36-45)",IF(C87="46-55","Pre-retirement (46-55)","Seniors (55+)")))) -> Young professionals (26-35)
A88: 87 | B88: Female | C88: 26-35 | D88: 2 | E88: Salaried | F88: 1L-2L | G88: 3 | H88: Nexon | I88: Petrol | J88: Manual | K88: 18L-25L | L88: 3 | M88: City Commute | N88: Safety | O88: Ground Clearance | P88: Budget | Q88: 360 Camera | R88: Website | S88: Loan | T88: Birthday | U88: Select Cars | V88: Moosapet | W88: Test Drive | X88: Yes | Y88: Yes | AA88: Parts availability | AB88: Service Competence & Capacity | AC88: =IF(H88="Punch","Entry",IF(OR(H88="Nexon",H88="Curvv"),"Compact","Premium")) -> Compact | AD88: =IF(C88="18-25","Gen Z (18-25)",IF(C88="26-35","Young professionals (26-35)",IF(C88="36-45","Family builders (36-45)",IF(C88="46-55","Pre-retirement (46-55)","Seniors (55+)")))) -> Young professionals (26-35)
A89: 88 | B89: Male | C89: 26-35 | D89: 2 | E89: Salaried | F89: 1L-2L | G89: 3 | H89: Harrier | I89: Diesel | J89: Automatic | K89: 18L-25L | L89: 3 | M89: Highway/Long Distance | N89: Safety | O89: Spaciousness | P89: Status | Q89: Ventilated Seats | R89: Word of Mouth | S89: Loan | T89: Festival | U89: Venkataramana Motors | V89: Not recorded | W89: Reputation | X89: No | Y89: Yes | AA89: Plastic quality | AB89: Fit & Finish | AC89: =IF(H89="Punch","Entry",IF(OR(H89="Nexon",H89="Curvv"),"Compact","Premium")) -> Premium | AD89: =IF(C89="18-25","Gen Z (18-25)",IF(C89="26-35","Young professionals (26-35)",IF(C89="36-45","Family builders (36-45)",IF(C89="46-55","Pre-retirement (46-55)","Seniors (55+)")))) -> Young professionals (26-35)
A90: 89 | B90: Male | C90: 46-55 | D90: 4 | E90: Business | F90: Above 2L | G90: 4 | H90: Safari | I90: Diesel | J90: Automatic | K90: Above 25L | L90: 4 | M90: Highway/Long Distance | N90: Safety | O90: Spaciousness | P90: Status | Q90: Ventilated Seats | R90: Website | S90: Cheque | T90: Festival | U90: Tejaswi Motors | V90: Hi-Tech | W90: Proximity | X90: No | Y90: Yes | AA90: Service response | AB90: Service Competence & Capacity | AC90: =IF(H90="Punch","Entry",IF(OR(H90="Nexon",H90="Curvv"),"Compact","Premium")) -> Premium | AD90: =IF(C90="18-25","Gen Z (18-25)",IF(C90="26-35","Young professionals (26-35)",IF(C90="36-45","Family builders (36-45)",IF(C90="46-55","Pre-retirement (46-55)","Seniors (55+)")))) -> Pre-retirement (46-55)
A91: 90 | B91: Male | C91: 36-45 | D91: 3 | E91: Homemaker | F91: 50K-1L | G91: 2 | H91: Harrier | I91: EV | J91: Manual | K91: 10L-18L | L91: 2 | M91: Highway/Long Distance | N91: Safety | O91: Styling | P91: Tech | Q91: Acti.ev Tech | R91: Website | S91: Loan | T91: Anniversary | U91: Venkataramana Motors | V91: Not recorded | W91: Reputation | X91: No | Y91: Yes | AA91: Fit and finish | AB91: Fit & Finish | AC91: =IF(H91="Punch","Entry",IF(OR(H91="Nexon",H91="Curvv"),"Compact","Premium")) -> Premium | AD91: =IF(C91="18-25","Gen Z (18-25)",IF(C91="26-35","Young professionals (26-35)",IF(C91="36-45","Family builders (36-45)",IF(C91="46-55","Pre-retirement (46-55)","Seniors (55+)")))) -> Family builders (36-45)
A92: 91 | B92: Male | C92: 46-55 | D92: 4 | E92: Business | F92: Above 2L | G92: 4 | H92: Curvv | I92: Petrol | J92: Automatic | K92: Above 25L | L92: 4 | M92: City Commute | N92: Safety | O92: Styling | P92: Status | Q92: 360 Camera | R92: Word of Mouth | S92: Cheque | T92: Anniversary | U92: Venkataramana Motors | V92: Not recorded | W92: Reputation | X92: No | Y92: Yes | AA92: Fit and finish | AB92: Fit & Finish | AC92: =IF(H92="Punch","Entry",IF(OR(H92="Nexon",H92="Curvv"),"Compact","Premium")) -> Compact | AD92: =IF(C92="18-25","Gen Z (18-25)",IF(C92="26-35","Young professionals (26-35)",IF(C92="36-45","Family builders (36-45)",IF(C92="46-55","Pre-retirement (46-55)","Seniors (55+)")))) -> Pre-retirement (46-55)
A93: 92 | B93: Male | C93: 26-35 | D93: 2 | E93: Salaried | F93: Below 50K | G93: 1 | H93: Nexon | I93: Petrol | J93: Manual | K93: Below 10L | L93: 1 | M93: City Commute | N93: Safety | O93: Ground Clearance | P93: Budget | Q93: Sunroof | R93: YouTube | S93: Loan | T93: Festival | U93: Select Cars | V93: Moosapet | W93: Test Drive | X93: Yes | Y93: No | Z93: Brand Trust | AA93: Parts availability | AB93: Service Competence & Capacity | AC93: =IF(H93="Punch","Entry",IF(OR(H93="Nexon",H93="Curvv"),"Compact","Premium")) -> Compact | AD93: =IF(C93="18-25","Gen Z (18-25)",IF(C93="26-35","Young professionals (26-35)",IF(C93="36-45","Family builders (36-45)",IF(C93="46-55","Pre-retirement (46-55)","Seniors (55+)")))) -> Young professionals (26-35)
A94: 93 | B94: Female | C94: 26-35 | D94: 2 | E94: Salaried | F94: 1L-2L | G94: 3 | H94: Curvv | I94: CNG | J94: Manual | K94: 18L-25L | L94: 3 | M94: City Commute | N94: Safety | O94: Styling | P94: Status | Q94: 360 Camera | R94: Website | S94: Loan | T94: Birthday | U94: Tejaswi Motors | V94: Hi-Tech | W94: Proximity | X94: No | Y94: Yes | AA94: Infotainment lag | AB94: Software Instability | AC94: =IF(H94="Punch","Entry",IF(OR(H94="Nexon",H94="Curvv"),"Compact","Premium")) -> Compact | AD94: =IF(C94="18-25","Gen Z (18-25)",IF(C94="26-35","Young professionals (26-35)",IF(C94="36-45","Family builders (36-45)",IF(C94="46-55","Pre-retirement (46-55)","Seniors (55+)")))) -> Young professionals (26-35)
A95: 94 | B95: Male | C95: Above 55 | D95: 5 | E95: Retired | F95: 1L-2L | G95: 3 | H95: Safari | I95: Diesel | J95: Automatic | K95: 18L-25L | L95: 3 | M95: Highway/Long Distance | N95: Safety | O95: Spaciousness | P95: Status | Q95: Ventilated Seats | R95: Word of Mouth | S95: Cheque | T95: Anniversary | U95: Select Cars | V95: Moosapet | W95: Test Drive | X95: No | Y95: Yes | AA95: Panel gaps | AB95: Fit & Finish | AC95: =IF(H95="Punch","Entry",IF(OR(H95="Nexon",H95="Curvv"),"Compact","Premium")) -> Premium | AD95: =IF(C95="18-25","Gen Z (18-25)",IF(C95="26-35","Young professionals (26-35)",IF(C95="36-45","Family builders (36-45)",IF(C95="46-55","Pre-retirement (46-55)","Seniors (55+)")))) -> Seniors (55+)
A96: 95 | B96: Female | C96: 18-25 | D96: 1 | E96: Salaried | F96: Below 50K | G96: 1 | H96: Punch | I96: Diesel | J96: Automatic | K96: Below 10L | L96: 1 | M96: City Commute | N96: Safety | O96: Ground Clearance | P96: Budget | Q96: Sunroof | R96: Website | S96: Loan | T96: Festival | U96: Venkataramana Motors | V96: Not recorded | W96: Reputation | X96: Yes | Y96: Yes | AA96: Fit and finish | AB96: Fit & Finish | AC96: =IF(H96="Punch","Entry",IF(OR(H96="Nexon",H96="Curvv"),"Compact","Premium")) -> Entry | AD96: =IF(C96="18-25","Gen Z (18-25)",IF(C96="26-35","Young professionals (26-35)",IF(C96="36-45","Family builders (36-45)",IF(C96="46-55","Pre-retirement (46-55)","Seniors (55+)")))) -> Gen Z (18-25)
A97: 96 | B97: Male | C97: 36-45 | D97: 3 | E97: Business | F97: Above 2L | G97: 4 | H97: Harrier | I97: CNG | J97: Automatic | K97: Above 25L | L97: 4 | M97: Highway/Long Distance | N97: Safety | O97: Spaciousness | P97: Status | Q97: 360 Camera | R97: YouTube | S97: Loan | T97: Festival | U97: Tejaswi Motors | V97: Hi-Tech | W97: Proximity | X97: No | Y97: Yes | AA97: Service response | AB97: Service Competence & Capacity | AC97: =IF(H97="Punch","Entry",IF(OR(H97="Nexon",H97="Curvv"),"Compact","Premium")) -> Premium | AD97: =IF(C97="18-25","Gen Z (18-25)",IF(C97="26-35","Young professionals (26-35)",IF(C97="36-45","Family builders (36-45)",IF(C97="46-55","Pre-retirement (46-55)","Seniors (55+)")))) -> Family builders (36-45)
A98: 97 | B98: Male | C98: 18-25 | D98: 1 | E98: Salaried | F98: 1L-2L | G98: 3 | H98: Curvv | I98: Diesel | J98: Manual | K98: 18L-25L | L98: 3 | M98: City Commute | N98: Safety | O98: Styling | P98: Status | Q98: 360 Camera | R98: Word of Mouth | S98: Loan | T98: Festival | U98: Select Cars | V98: Moosapet | W98: Test Drive | X98: No | Y98: Yes | AA98: Panel gaps | AB98: Fit & Finish | AC98: =IF(H98="Punch","Entry",IF(OR(H98="Nexon",H98="Curvv"),"Compact","Premium")) -> Compact | AD98: =IF(C98="18-25","Gen Z (18-25)",IF(C98="26-35","Young professionals (26-35)",IF(C98="36-45","Family builders (36-45)",IF(C98="46-55","Pre-retirement (46-55)","Seniors (55+)")))) -> Gen Z (18-25)
A99: 98 | B99: Male | C99: 26-35 | D99: 2 | E99: Salaried | F99: 50K-1L | G99: 2 | H99: Nexon | I99: Petrol | J99: Manual | K99: 10L-18L | L99: 2 | M99: City Commute | N99: Safety | O99: Ground Clearance | P99: Budget | Q99: Sunroof | R99: Word of Mouth | S99: Loan | T99: Festival | U99: Select Cars | V99: Moosapet | W99: Test Drive | X99: Yes | Y99: No | Z99: Brand Trust | AA99: Panel gaps | AB99: Fit & Finish | AC99: =IF(H99="Punch","Entry",IF(OR(H99="Nexon",H99="Curvv"),"Compact","Premium")) -> Compact | AD99: =IF(C99="18-25","Gen Z (18-25)",IF(C99="26-35","Young professionals (26-35)",IF(C99="36-45","Family builders (36-45)",IF(C99="46-55","Pre-retirement (46-55)","Seniors (55+)")))) -> Young professionals (26-35)
A100: 99 | B100: Male | C100: 26-35 | D100: 2 | E100: Salaried | F100: 50K-1L | G100: 2 | H100: Harrier | I100: Petrol | J100: Automatic | K100: 10L-18L | L100: 2 | M100: Highway/Long Distance | N100: Safety | O100: Spaciousness | P100: Status | Q100: Ventilated Seats | R100: YouTube | S100: Loan | T100: Birthday | U100: Select Cars | V100: Moosapet | W100: Test Drive | X100: No | Y100: Yes | AA100: Parts availability | AB100: Service Competence & Capacity | AC100: =IF(H100="Punch","Entry",IF(OR(H100="Nexon",H100="Curvv"),"Compact","Premium")) -> Premium | AD100: =IF(C100="18-25","Gen Z (18-25)",IF(C100="26-35","Young professionals (26-35)",IF(C100="36-45","Family builders (36-45)",IF(C100="46-55","Pre-retirement (46-55)","Seniors (55+)")))) -> Young professionals (26-35)
A101: 100 | B101: Male | C101: 46-55 | D101: 4 | E101: Homemaker | F101: 50K-1L | G101: 2 | H101: Nexon | I101: CNG | J101: Manual | K101: 10L-18L | L101: 2 | M101: City Commute | N101: Safety | O101: Ground Clearance | P101: Budget | Q101: 360 Camera | R101: Word of Mouth | S101: Loan | T101: Anniversary | U101: Select Cars | V101: Moosapet | W101: Test Drive | X101: Yes | Y101: No | Z101: Brand Trust | AA101: Panel gaps | AB101: Fit & Finish | AC101: =IF(H101="Punch","Entry",IF(OR(H101="Nexon",H101="Curvv"),"Compact","Premium")) -> Compact | AD101: =IF(C101="18-25","Gen Z (18-25)",IF(C101="26-35","Young professionals (26-35)",IF(C101="36-45","Family builders (36-45)",IF(C101="46-55","Pre-retirement (46-55)","Seniors (55+)")))) -> Pre-retirement (46-55)
...

Sheet Notes
B1: Notes, definitions and how to extend this workbook
B3: Sheets
B4: Executive_Summary: KPI tiles, eight formula-driven findings and two charts.
B5: Demand_Profile, Powertrain_Transmission, Buying_Behaviour, Service_Experience: analysis tables (COUNTIFS on the Data sheet) with charts.
B6: Segment_Scorecard: five life-stage segments compared on EV, automatic, loan and premium share.
B7: Data: cleaned survey (135 rows) plus two helper columns, Model_Tier and Life_Stage, that are formulas.
B8: Definitions
B9: Model_Tier: Entry = Punch; Compact = Nexon, Curvv; Premium = Harrier, Safari, Sierra (analyst grouping).
B10: Life_Stage: Gen Z 18-25; Young professionals 26-35; Family builders 36-45; Pre-retirement 46-55; Seniors 55+ (age-based labels).
B11: Complaint themes: Software = software stability + infotainment lag; Service = service response + parts availability; Fit & Finish = panel gaps + plastic quality + fit and finish.
B12: Avg budget index: 1 = Below 10L, 2 = 10L-18L, 3 = 18L-25L, 4 = Above 25L.
B13: Row order on some tables (models, complaints) reflects the current counts. If you change the data, re-sort them.
... B22: Convenience sample; single city; single time point. Small segments (for example 55+, n=16) are indicative only.
